Workbook
Name Index_Sheet_Kutools: #REF!

Sheet new
A1: Keep as many sheets are linked to it
A2: rme | B2: rm | C2: rme_label | D2: rm_label
A3: RME001 | B3: RM001 | C3: Cereals | D3: Cereals
A4: RME002 | B4: RM002 | C4: Green vegetables | D4: Green vegetables
A5: RME003 | B5: RM003 | C5: Dried vegetables | D5: Dried vegetables/pulses
A6: RME004 | B6: RM004 | C6: Soya, oil seeds | D6: Soya, oil seeds
A7: RME005 | B7: RM005 | C7: Roots, tubers | D7: Roots, tubers
A8: RME006 | B8: RM006 | C8: Sugar beet, cane | D8: Sugar beet, cane
A9: RME007 | B9: RM007 | C9: Tobacco | D9: Tobacco
A10: RME008 | B10: RM008 | C10: Fibre crops | D10: Fibre crops
A11: RME009 | B11: RM009 | C11: Forage crops, grazing | D11: Forage crops, grazing
A12: RME010 | B12: RM010 | C12: Fruits | D12: Fruits
A13: RME011 | B13: RM011 | C13: Other crops | D13: Other crops
... A192: : | B192: : | C192: : | D192: :

Sheet rm
A2: rm | B2: cpa | C2: rme | D2: rm_sbs | E2: rm_unido | F2: rm_label
A3: RM001 | B3: CPA_A01 | C3: RME001 | D3: : | E3: : | F3: Cereals
A4: RM002 | B4: CPA_A01 | C4: RME002 | D4: : | E4: : | F4: Green vegetables
A5: RM003 | B5: CPA_A01 | C5: RME003 | D5: : | E5: : | F5: Dried vegetables/Pulses
A6: RM004 | B6: CPA_A01 | C6: RME004 | D6: : | E6: : | F6: Soya, oil seeds
A7: RM005 | B7: CPA_A01 | C7: RME005 | D7: : | E7: : | F7: Roots, tubers
A8: RM006 | B8: CPA_A01 | C8: RME006 | D8: : | E8: : | F8: Sugar beet, cane
A9: RM007 | B9: CPA_A01 | C9: RME007 | D9: : | E9: : | F9: Tobacco
A10: RM008 | B10: CPA_A01 | C10: RME008 | D10: : | E10: : | F10: Fibre crops
A11: RM009 | B11: CPA_A01 | C11: RME009 | D11: : | E11: : | F11: Forage crops, grazing
A12: RM010 | B12: CPA_A01 | C12: RME010 | D12: : | E12: : | F12: Fruits
A13: RM011 | B13: CPA_A01 | C13: RME011 | D13: : | E13: : | F13: Other crops
... A168: RM166 | B168: CPA_U | C168: RME181 | D168: RM166 | E168: RM166 | F168: Extraterritorial organisations
A169: HFCE | B169: HFCE | C169: HFCE
A170: NFCE | B170: NFCE | C170: NFCE
A171: GFCE | B171: GFCE | C171: GFCE
A172: INV | B172: INV | C172: INV
A173: CINV | B173: CINV | C173: CINV
A174: OUT | B174: OUT | C174: OUT
A175: GVA | B175: GVA | C175: GVA | D175: GVA | E175: GVA
A176: RM038-044 | B176: CPA_B
A177: RM088-097 | B177: CPA_C24
A178: RM023_025 | B178: CPA_B
A179: RM027-037 | B179: CPA_B
A180: RM045-047 | B180: CPA_B
A181: RM028-037 | B181: CPA_B
A182: RM038-041 | B182: CPA_B
A183: RM042-044 | B183: CPA_B
A184: RM088-090 | B184: CPA_C24
A185: RM092-094 | B185: CPA_C24
A186: RM096-097 | B186: CPA_C24

Sheet rmh
A2: rmh | B2: rm | C2: rmh_label | D2: cpa | E2: cpa_detailed | F2: rm_label_long
A3: RM001 | B3: RM001 | C3: Cereals | D3: CPA_A01 | E3: 01.11.1-4, 01.12 | F3: Cereals (excl. cereals straw and husk), rice
A4: RM002 | B4: RM002 | C4: Green vegetables | D4: CPA_A01 | E4: 01.11.6, 01.13 (excl. 01.13.5, 01.13.7) | F4: Green leguminous vegetables, vegetables and melons ( excl. edible roots and tubers and sugar beet)
A5: RM003 | B5: RM003 | C5: Dried vegetables/Pulses | D5: CPA_A01 | E5: 01.11.7 | F5: Dried leguminous vegetables
A6: RM004 | B6: RM004 | C6: Soya, oil seeds | D6: CPA_A01 | E6: 01.11.8, 01.11.9, 01.26.1 | F6: Soya beans, groundnuts and cotton seed, other oil seeds
A7: RM005 | B7: RM005 | C7: Roots, tubers | D7: CPA_A01 | E7: 01.13.5 | F7: Edible roots and tubers with high starch or inulin conten
A8: RM006 | B8: RM006 | C8: Sugar beet, cane | D8: CPA_A01 | E8: 01.13.7, 01.14 | F8: Sugar beet and sugar beet seed, sugar cane
A9: RM007 | B9: RM007 | C9: Tobacco | D9: CPA_A01 | E9: 01.15 | F9: Unmanufactured tobacco
A10: RM008 | B10: RM008 | C10: Fibre crops | D10: CPA_A01 | E10: 01.16 | F10: Fibre crops
A11: RM009 | B11: RM009 | C11: Forage crops, grazing | D11: CPA_A01 | E11: 01.19.1, 01.11.5 | F11: Forage crops
A12: RM010 | B12: RM010 | C12: Fruits | D12: CPA_A01 | E12: 01.2 (excl. 01.25.3, 01.26.1, 01.27, 01.28. 10.29) | F12: Fruits
A13: RM011 | B13: RM011 | C13: Other crops | D13: CPA_A01 | E13: 01.19.2, 01.19.3, 01.25.3, 01.27, 01.28, 01.29, 01.3 | F13: Other crop products
... A21: RM019.1 | B21: RM019 | C21: Forestry | D21: CPA_A02 | E21: 02 | F21: Products of forestry, logging and related services
A22: RM019.2 | B22: RM019 | C22: Fuel woord, other primary solid biofuels | D22: CPA_A02
A23: RM020 | B23: RM020 | C23: Fish | D23: CPA_A03 | E23: 03 | F23: Fish and other fishing products; aquaculture products; support services to fishing
A24: RM021 | B24: RM021 | C24: Hard coal | D24: CPA_B | E24: 05.1 | F24: Hard coal
A25: RM022 | B25: RM022 | C25: Lignite | D25: CPA_B | E25: 05.2 | F25: Lignite, incl. peat for energetic use
A26: RM023 | B26: RM023 | C26: Petroleum oils | D26: CPA_B | E26: 06.10.1 | F26: Petroleum oils and oils obtained from bituminous minerals, crude
A27: RM024 | B27: RM024 | C27: Oil shale, tar sands | D27: CPA_B | E27: 06.10.2 | F27: Bituminous or oil shale and tar sands
A28: RM025 | B28: RM025 | C28: Natural gas | D28: CPA_B | E28: 06.2 | F28: Natural gas, liquefied or in gaseous state
A29: RM026 | B29: RM026 | C29: Iron ores | D29: CPA_B | E29: 07.1 | F29: Iron ores
A30: RM027 | B30: RM027 | C30: Uranium ores | D30: CPA_B | E30: 07.21 | F30: Uranium and thorium ores
A31: RM028 | B31: RM028 | C31: Copper ores | D31: CPA_B | E31: 07.29.11 | F31: Copper ores and concentrates
A32: RM029 | B32: RM029 | C32: Nickel ores | D32: CPA_B | E32: 07.29.12 | F32: Nickel ores and concentrates
A33: RM030 | B33: RM030 | C33: Aluminium ores | D33: CPA_B | E33: 07.29.13 | F33: Aluminium ores and concentrates
A34: RM031 | B34: RM031 | C34: Gold ores | D34: CPA_B | E34: 07.29.14.a | F34: Gold ores and concentrates
... A184: RM166 | B184: RM166 | C184: Extraterritorial organisations | D184: CPA_U | E184: 99 | F184: Extraterritorial organisations

Sheet iso2
A1: last update: 10.12.2025 (inclusion of column for BGS data)
A2: iso2 | B2: iso3 | C2: name_short | D2: prodcom | E2: wmd | F2: bgs | G2: irp_published | H2: iea | I2: unido | J2: baci | K2: fao | L2: eu | M2: 2r | N2: eu_iciot | O2: icio | P2: non_eu | Q2: 2r_trade | R2: regex
A3: : | B3: : | C3: China, Mainland | D3: : | E3: : | F3: China, Mainland | G3: China, Mainland | H3: : | I3: : | J3: : | K3: 41 | L3: : | M3: : | N3: : | O3: : | P3: :
A4: : | B4: : | C4: Ethiopia PDR (historic) | D4: : | E4: : | F4: Ethiopia PDR (historic) | G4: Ethiopia PDR (historic) | H4: : | I4: : | J4: : | K4: 62 | L4: : | M4: : | N4: : | O4: : | P4: :
A5: : | B5: : | C5: Africa | D5: : | E5: : | F5: Africa | G5: Africa | H5: : | I5: : | J5: : | K5: 5100 | L5: : | M5: : | N5: : | O5: : | P5: :
A6: : | B6: : | C6: Eastern Africa | D6: : | E6: : | F6: Eastern Africa | G6: Eastern Africa | H6: : | I6: : | J6: : | K6: 5101 | L6: : | M6: : | N6: : | O6: : | P6: :
A7: : | B7: : | C7: Middle Africa | D7: : | E7: : | F7: Middle Africa | G7: Middle Africa | H7: : | I7: : | J7: : | K7: 5102 | L7: : | M7: : | N7: : | O7: : | P7: :
A8: : | B8: : | C8: Northern Africa | D8: : | E8: : | F8: Northern Africa | G8: Northern Africa | H8: : | I8: : | J8: : | K8: 5103 | L8: : | M8: : | N8: : | O8: : | P8: :
A9: : | B9: : | C9: Southern Africa | D9: : | E9: : | F9: Southern Africa | G9: Southern Africa | H9: : | I9: : | J9: : | K9: 5104 | L9: : | M9: : | N9: : | O9: : | P9: :
A10: : | B10: : | C10: Western Africa | D10: : | E10: : | F10: Western Africa | G10: Western Africa | H10: : | I10: : | J10: : | K10: 5105 | L10: : | M10: : | N10: : | O10: : | P10: :
A11: : | B11: : | C11: Americas | D11: : | E11: : | F11: Americas | G11: Americas | H11: : | I11: : | J11: : | K11: 5200 | L11: : | M11: : | N11: : | O11: : | P11: :
A12: : | B12: : | C12: North America | D12: : | E12: : | F12: North America | G12: North America | H12: : | I12: : | J12: : | K12: 5203 | L12: : | M12: : | N12: : | O12: : | P12: :
A13: : | B13: : | C13: Central America | D13: : | E13: : | F13: Central America | G13: Central America | H13: : | I13: : | J13: : | K13: 5204 | L13: : | M13: : | N13: : | O13: : | P13: :
A14: : | B14: : | C14: Caribbean | D14: : | E14: : | F14: Caribbean | G14: Caribbean | H14: : | I14: : | J14: : | K14: 5206 | L14: : | M14: : | N14: : | O14: : | P14: :
... A36: : | B36: : | C36: Net Food Importing Developing Countries | D36: : | E36: : | F36: Net Food Importing Developing Countries | G36: Net Food Importing Developing Countries | H36: : | I36: : | J36: : | K36: 5817 | L36: : | M36: : | N36: : | O36: : | P36: :
A37: : | H37: G7 | N37: : | O37: :
A38: : | H38: IEA and Accession/Association countries | N38: : | O38: :
A39: : | H39: OECD Americas | N39: : | O39: :
A40: : | H40: OECD Asia Oceania | N40: : | O40: :
A41: : | H41: OECD Europe | N41: : | O41: :
A42: : | H42: OECD Total | N42: : | O42: :
A43: : | H43: Total IEA | N43: : | O43: :
A44: AD | B44: AND | C44: Andorra | F44: Andorra | G44: Andorra | J44: 20 | K44: 6 | L44: RoW | M44: WN | N44: WX | O44: WX | P44: WX | Q44: _e | R44: andorra
A45: AE | B45: ARE | C45: United Arab Emirates | E45: United Arab Emirates | F45: United Arab Emirates | G45: United Arab Emirates | H45: United Arab Emirates | I45: 784 | J45: 784 | K45: 225 | L45: RoW | M45: WN | N45: WX | O45: WX | P45: WX | Q45: _e | R45: emirates|^u\.?a\.?e\.?$|united.?arab.?em
A46: AF | B46: AFG | C46: Afghanistan | E46: Afghanistan | F46: Afghanistan | G46: Afghanistan | H46: Afghanistan | I46: 004 | J46: 4 | K46: 2 | L46: RoW | M46: WN | N46: WX | O46: WX | P46: WX | Q46: _e | R46: afghan
A47: AFR_OTH | C47: Other Africa | F47: Other Africa | G47: Other Africa | K47: : | M47: WN | N47: WX | O47: WX | P47: WX | Q47: _e
A48: AG | B48: ATG | C48: Antigua and Barbuda | F48: Antigua and Barbuda | G48: Antigua and Barbuda | H48: Antigua and Barbuda | I48: 028 | J48: 28 | K48: 8 | L48: RoW | M48: WN | N48: WX | O48: WX | P48: WX | Q48: _e | R48: antigua
A49: AI | B49: AIA | C49: Anguilla | F49: Anguilla | G49: Anguilla | J49: 660 | K49: 258 | L49: RoW | M49: WN | N49: WX | O49: WX | P49: WX | Q49: _e | R49: anguill?a
A50: AL | B50: ALB | C50: Albania | D50: 070 | E50: Albania | F50: Albania | G50: Albania | H50: Albania | I50: 008 | J50: 8 | K50: 3 | L50: RoW | M50: WN | N50: WX | O50: WX | P50: WX | Q50: _e | R50: albania
A51: AM | B51: ARM | C51: Armenia | E51: Armenia | F51: Armenia | G51: Armenia | H51: Armenia | I51: 051 | J51: 51 | K51: 1 | L51: RoW | M51: WN | N51: WX | O51: WX | P51: WX | Q51: _e | R51: armenia
A52: AME_OTH | C52: Other Americas | F52: Other Americas | G52: Other Americas | K52: : | M52: WN | O52: : | P52: : | Q52: _e
A53: AN | B53: ANT | C53: Netherlands Antilles | F53: Netherlands Antilles | G53: Netherlands Antilles | H53: Netherlands Antilles | J53: 530 | K53: 151 | L53: RoW | M53: WN | N53: WX | O53: WX | P53: WX | Q53: _e | R53: antilles
A54: AO | B54: AGO | C54: Angola | E54: Angola | F54: Angola | G54: Angola | H54: Angola | I54: 024 | J54: 24 | K54: 7 | L54: RoW | M54: WN | N54: WX | O54: WX | P54: WX | Q54: _e | R54: angola
A55: AQ | B55: ATA | C55: Antarctica | F55: Antarctica | G55: Antarctica | K55: 30 | L55: RoW | M55: WN | N55: WX | O55: WX | P55: WX | Q55: _e | R55: antarctica
A56: AR | B56: ARG | C56: Argentina | E56: Argentina | F56: Argentina | G56: Argentina | H56: Argentina | I56: 032 | J56: 32 | K56: 9 | L56: RoW | M56: WN | N56: WX | O56: AR | P56: AR | Q56: _e | R56: argentin
A57: AS | B57: ASM | C57: American Samoa | F57: American Samoa | G57: American Samoa | J57: 16 | K57: 5 | L57: RoW | M57: WN | N57: WX | O57: WX | P57: WX | Q57: _e | R57: ^(?=.*americ).*samoa
A58: ASI_NME_OTH | C58: Other Asia | F58: Other Asia | G58: Other Asia | K58: : | M58: WN | O58: : | P58: : | Q58: _e
A59: ASI_OTH | K59: : | M59: WN | O59: : | P59: : | Q59: _e
A60: AT | B60: AUT | C60: Austria | D60: 038 | E60: Austria | F60: Austria | G60: Austria | H60: Austria | I60: 040 | J60: 40 | K60: 11 | L60: AT | M60: EU27 | N60: AT | O60: AT | P60: EU27 | Q60: _i | R60: austria
A61: AU | B61: AUS | C61: Australia | E61: Australia | F61: Australia | G61: Australia | H61: Australia | I61: 036 | J61: 36 | K61: 10 | L61: RoW | M61: WN | N61: WX | O61: AU | P61: AU | Q61: _e | R61: australia
A62: AW | B62: ABW | C62: Aruba | F62: Aruba | G62: Aruba | H62: Aruba | J62: 533 | K62: 22 | L62: RoW | M62: WN | N62: WX | O62: WX | P62: WX | Q62: _e | R62: ^(?!.*bonaire).*\baruba
A63: AX | B63: ALA | C63: Aland Islands | F63: Aland Islands | G63: Aland Islands | K63: 284 | L63: FI | M63: EU27 | N63: FI | O63: FI | P63: EU27 | Q63: _i | R63: \b(a|å)land
A64: AZ | B64: AZE | C64: Azerbaijan | E64: Azerbaijan | F64: Azerbaijan | G64: Azerbaijan | H64: Azerbaijan | I64: 031 | J64: 31 | K64: 52 | L64: RoW | M64: WN | N64: WX | O64: WX | P64: WX | Q64: _e | R64: azerbaijan
A65: BA | B65: BIH | C65: Bosnia and Herzegovina | D65: 093 | E65: Bosnia-Herzegovina | F65: Bosnia & Herzegovina | G65: Bosnia and Herzegovina | H65: Bosnia and Herzegovina | I65: 070 | J65: 70 | K65: 80 | L65: RoW | M65: WN | N65: WX | O65: WX | P65: WX | Q65: _e | R65: herzegovina|bosnia
A66: BB | B66: BRB | C66: Barbados | E66: Barbados | F66: Barbados | G66: Barbados | H66: Barbados | J66: 52 | K66: 14 | L66: RoW | M66: WN | N66: WX | O66: WX | P66: WX | Q66: _e | R66: barbados
A67: BD | B67: BGD | C67: Bangladesh | E67: Bangladesh | F67: Bangladesh | G67: Bangladesh | H67: Bangladesh | I67: 050 | J67: 50 | K67: 16 | L67: RoW | M67: WN | N67: WX | O67: WX | P67: WX | Q67: _e | R67: bangladesh|^(?=.*east).*paki?stan
A68: BE | B68: BEL | C68: Belgium | D68: 017 | E68: Belgium | F68: Belgium | G68: Belgium | H68: Belgium | I68: 056 | J68: 56 | K68: 255 | L68: BE | M68: EU27 | N68: BE | O68: BE | P68: EU27 | Q68: _i | R68: ^(?!.*luxem).*belgium
A69: BF | B69: BFA | C69: Burkina Faso | E69: Burkina Faso | F69: Burkina Faso | G69: Burkina Faso | H69: Burkina Faso | I69: 854 | J69: 854 | K69: 233 | L69: RoW | M69: WN | N69: WX | O69: WX | P69: WX | Q69: _e | R69: burkina|\bfaso|upper.?volta
A70: BG | B70: BGR | C70: Bulgaria | D70: 068 | E70: Bulgaria | F70: Bulgaria | G70: Bulgaria | H70: Bulgaria | I70: 100 | J70: 100 | K70: 27 | L70: BG | M70: EU27 | N70: BG | O70: BG | P70: EU27 | Q70: _i | R70: bulgaria
A71: BH | B71: BHR | C71: Bahrain | E71: Bahrain | F71: Bahrain | G71: Bahrain | H71: Bahrain | I71: 048 | J71: 48 | K71: 13 | L71: RoW | M71: WN | N71: WX | O71: WX | P71: WX | Q71: _e | R71: bahrain
A72: BI | B72: BDI | C72: Burundi | E72: Burundi | F72: Burundi | G72: Burundi | H72: Burundi | I72: 108 | J72: 108 | K72: 29 | L72: RoW | M72: WN | N72: WX | O72: WX | P72: WX | Q72: _e | R72: burundi
A73: BJ | B73: BEN | C73: Benin | E73: Benin | F73: Benin | G73: Benin | H73: Benin | I73: 204 | J73: 204 | K73: 53 | L73: RoW | M73: WN | N73: WX | O73: WX | P73: WX | Q73: _e | R73: benin|dahome
A74: BL | B74: BLM | C74: St. Barths | F74: St. Barths | G74: St. Barths | H74: St. Barths | J74: 652 | K74: 282 | L74: RoW | M74: WN | N74: WX | O74: WX | P74: WX | Q74: _e | R74: barth|barts
A75: BLG | B75: BLG | C75: Belgium-Luxemburg (historic) | F75: Belgium-Luxemburg (historic) | G75: Belgium-Luxemburg (historic) | H75: Belgium-Luxemburg (historic) | K75: 15 | L75: : | M75: : | N75: : | O75: : | P75: : | Q75: :
A76: BM | B76: BMU | C76: Bermuda | F76: Bermuda | G76: Bermuda | H76: Bermuda | I76: 060 | J76: 60 | K76: 17 | L76: RoW | M76: WN | N76: WX | O76: WX | P76: WX | Q76: _e | R76: bermuda
A77: BN | B77: BRN | C77: Brunei Darussalam | E77: Brunei | F77: Brunei Darussalam | G77: Brunei Darussalam | H77: Brunei Darussalam | I77: 096 | J77: 96 | K77: 26 | L77: RoW | M77: WN | N77: WX | O77: WX | P77: WX | Q77: _e | R77: brunei
A78: BO | B78: BOL | C78: Bolivia | E78: Bolivia | F78: Bolivia | G78: Bolivia | H78: Bolivia | I78: 068 | J78: 68 | K78: 19 | L78: RoW | M78: WN | N78: WX | O78: WX | P78: WX | Q78: _e | R78: bolivia
A79: BQ | B79: BES | C79: Bonaire, Saint Eustatius and Saba | F79: Bonaire, Saint Eustatius and Saba | G79: Bonaire, Saint Eustatius and Saba | H79: Bonaire, Saint Eustatius and Saba | J79: 535 | K79: 278 | L79: RoW | M79: WN | N79: WX | O79: WX | P79: WX | Q79: _e | R79: ^(?=.*bonaire).*eustatius|^(?=.*carib).*netherlands|\bbes.?islands
A80: BQ_old | C80: British Antarctic Territory | F80: British Antarctic Territory | G80: British Antarctic Territory | H80: British Antarctic Territory | K80: : | L80: RoW | M80: WN | N80: WX | O80: WX | P80: WX | Q80: _e
A81: BR | B81: BRA | C81: Brazil | E81: Brazil | F81: Brazil | G81: Brazil | H81: Brazil | I81: 076 | J81: 76 | K81: 21 | L81: RoW | M81: WN | N81: WX | O81: BR | P81: BR | Q81: _e | R81: brazil
A82: BS | B82: BHS | C82: Bahamas | E82: Bahamas | F82: Bahamas | G82: Bahamas | H82: Bahamas | I82: 044 | J82: 44 | K82: 12 | L82: RoW | M82: WN | N82: WX | O82: WX | P82: WX | Q82: _e | R82: bahamas
A83: BT | B83: BTN | C83: Bhutan | E83: Bhutan | F83: Bhutan | G83: Bhutan | H83: Bhutan | I83: 064 | J83: 64 | K83: 18 | L83: RoW | M83: WN | N83: WX | O83: WX | P83: WX | Q83: _e | R83: bhutan
A84: BUNA | C84: World aviation bunkers | F84: World aviation bunkers | G84: World aviation bunkers | K84: : | N84: World aviation bunkers | O84: World aviation bunkers | P84: World aviation bunkers
A85: BUNM | C85: World marine bunkers | F85: World marine bunkers | G85: World marine bunkers | K85: : | N85: World marine bunkers | O85: World marine bunkers | P85: World marine bunkers
A86: BV | B86: BVT | C86: Bouvet Island | F86: Bouvet Island | G86: Bouvet Island | H86: Bouvet Island | K86: 31 | L86: RoW | M86: WN | N86: WX | O86: WX | P86: WX | Q86: _e | R86: bouvet
A87: BW | B87: BWA | C87: Botswana | E87: Botswana | F87: Botswana | G87: Botswana | H87: Botswana | I87: 072 | J87: 72 | K87: 20 | L87: RoW | M87: WN | N87: WX | O87: WX | P87: WX | Q87: _e | R87: botswana|bechuana
A88: BY | B88: BLR | C88: Belarus | E88: Belarus | F88: Belarus | G88: Belarus | H88: Belarus | I88: 112 | J88: 112 | K88: 57 | L88: RoW | M88: WN | N88: WX | O88: WX | P88: WX | Q88: _e | R88: belarus|byelo
A89: BZ | B89: BLZ | C89: Belize | F89: Belize | G89: Belize | H89: Belize | I89: 084 | J89: 84 | K89: 23 | L89: RoW | M89: WN | N89: WX | O89: WX | P89: WX | Q89: _e | R89: belize|^(?=.*british).*honduras
A90: CA | B90: CAN | C90: Canada | E90: Canada | F90: Canada | G90: Canada | H90: Canada | I90: 124 | J90: 124 | K90: 33 | L90: RoW | M90: WN | N90: WX | O90: CA | P90: CA | Q90: _e | R90: canada
A91: CC | B91: CCK | C91: Cocos (Keeling) Islands | F91: Cocos (Keeling) Islands | G91: Cocos (Keeling) Islands | H91: Cocos (Keeling) Islands | J91: 166 | K91: 43 | L91: RoW | M91: WN | N91: WX | O91: WX | P91: WX | Q91: _e | R91: \bcocos|keeling
A92: CD | B92: COD | C92: DR Congo | E92: Congo, D.R. | F92: Congo, Democratic Republic | G92: DR Congo | H92: DR Congo | J92: 180 | K92: 250 | L92: RoW | M92: WN | N92: WX | O92: WX | P92: WX | Q92: _e | R92: \bdem.*congo|congo.*\bdem|congo.*\bdr|\bdr.*congo|\bd\.?r\.?c|\bd\.?r\.?o\.?c|\br\.?d\.?c|belgian.?congo|congo.?free.?state|kinshasa|zaire|l\w{1,2}opoldville|^the\ congo$|^RDC$|^DROC$|\bcongo.*dem.*
A93: CF | B93: CAF | C93: Central African Republic | E93: Central African Republic | F93: Central African Republic | G93: Central African Republic | H93: Central African Republic | J93: 140 | K93: 37 | L93: RoW | M93: WN | N93: WX | O93: WX | P93: WX | Q93: _e | R93: central.?african.?rep.*
A94: CG | B94: COG | C94: Congo Republic | E94: Congo, Rep. | F94: Congo | G94: Rep Congo | H94: Congo Republic | I94: 178 | J94: 178 | K94: 46 | L94: RoW | M94: WN | N94: WX | O94: WX | P94: WX | Q94: _e | R94: ^(?!.*\bdem)(?!.*\bdr)(?!.*kinshasa)(?!.*zaire)(?!.*belg)(?!.*l\w{1,2}opoldville)(?!.*free)(^rep.*).*\bcongo.*(?!.*\bdem)(?!.*\bdr).*|\bwest.*congo|^congo[,;\s]*(?!.*dem)rep.*?$|^congo$|\bcongo.*brazza.*
A95: CH | B95: CHE | C95: Switzerland | E95: Switzerland | F95: Switzerland | G95: Switzerland | H95: Switzerland | I95: 756 | J95: 757 | K95: 211 | L95: RoW | M95: WN | N95: WX | O95: CH | P95: CH | Q95: _e | R95: switz|swiss
A96: CI | B96: CIV | C96: Cote d'Ivoire | E96: Cote d'Ivoire | F96: Cote d'Ivoire | G96: Cote d'Ivoire | H96: Cote d'Ivoire | I96: 384 | J96: 384 | K96: 107 | L96: RoW | M96: WN | N96: WX | O96: WX | P96: WX | Q96: _e | R96: .*(ivoire|ivory)
A97: CK | B97: COK | C97: Cook Islands | F97: Cook Islands | G97: Cook Islands | H97: Cook Islands | J97: 184 | K97: 47 | L97: RoW | M97: WN | N97: WX | O97: WX | P97: WX | Q97: _e | R97: \bcook
A98: CL | B98: CHL | C98: Chile | E98: Chile | F98: Chile | G98: Chile | H98: Chile | I98: 152 | J98: 152 | K98: 40 | L98: RoW | M98: WN | N98: WX | O98: WX | P98: WX | Q98: _e | R98: \bchile
A99: CM | B99: CMR | C99: Cameroon | E99: Cameroon | F99: Cameroon | G99: Cameroon | H99: Cameroon | I99: 120 | J99: 120 | K99: 32 | L99: RoW | M99: WN | N99: WX | O99: WX | P99: WX | Q99: _e | R99: cameroon
A100: CN | B100: CHN | C100: China | E100: China | F100: China | G100: China | H100: China, People's Republic of | I100: 156 | J100: 156 | K100: 351 | L100: RoW | M100: WN | N100: WX | O100: CN | P100: CN | Q100: _e | R100: ^(?!repub)(?!taiwan)(?!hong.*kong)(?!macao).*china(?!.*hong.*kong)(?!.*macao)|^PRC$
A101: CO | B101: COL | C101: Colombia | E101: Colombia | F101: Colombia | G101: Colombia | H101: Colombia | I101: 170 | J101: 170 | K101: 44 | L101: RoW | M101: WN | N101: WX | O101: WX | P101: WX | Q101: _e | R101: colombia
A102: CR | B102: CRI | C102: Costa Rica | E102: Costa Rica | F102: Costa Rica | G102: Costa Rica | H102: Costa Rica | I102: 188 | J102: 188 | K102: 48 | L102: RoW | M102: WN | N102: WX | O102: WX | P102: WX | Q102: _e | R102: costa.?rica
A103: CSK | B103: CSK | C103: Czechslovakia (historic) | E103: Czechoslovakia | F103: Czechslovakia (historic) | G103: Czechslovakia (historic) | H103: Czechslovakia (historic) | K103: 51 | L103: : | M103: : | N103: : | O103: : | P103: : | Q103: :
A104: CU | B104: CUB | C104: Cuba | E104: Cuba | F104: Cuba | G104: Cuba | H104: Cuba | I104: 192 | J104: 192 | K104: 49 | L104: RoW | M104: WN | N104: WX | O104: WX | P104: WX | Q104: _e | R104: \bcuba
A105: CV | B105: CPV | C105: Cabo Verde | E105: Cape Verde | F105: Cabo Verde | G105: Cabo Verde | H105: Cabo Verde | I105: 132 | J105: 132 | K105: 35 | L105: RoW | M105: WN | N105: WX | O105: WX | P105: WX | Q105: _e | R105: (cabo|cape) *verde
A106: CW | B106: CUW | C106: Curacao | F106: Curacao | G106: Curacao | H106: Curacao | I106: 531 | J106: 531 | K106: 279 | L106: RoW | M106: WN | N106: WX | O106: WX | P106: WX | Q106: _e | R106: \bcura(c|ç)ao
A107: CX | B107: CXR | C107: Christmas Island | E107: Christmas Island | F107: Christmas Island | G107: Christmas Island | H107: Christmas Island | J107: 162 | K107: 42 | L107: RoW | M107: WN | N107: WX | O107: WX | P107: WX | Q107: _e | R107: christmas
A108: CY | B108: CYP | C108: Cyprus | D108: 600 | E108: Cyprus | F108: Cyprus | G108: Cyprus | H108: Cyprus | I108: 196 | J108: 196 | K108: 50 | L108: CY | M108: EU27 | N108: CY | O108: CY | P108: EU27 | Q108: _i | R108: cyprus
A109: CZ | B109: CZE | C109: Czech Republic | D109: 061 | E109: Czechia | F109: Czech Republic | G109: Czech Republic | H109: Czech Republic | I109: 203 | J109: 203 | K109: 167 | L109: CZ | M109: EU27 | N109: CZ | O109: CZ | P109: EU27 | Q109: _i | R109: ^(?=.*rep).*czech.*|czechia|bohemia|.*czech.*
A110: DDR | B110: DDR | C110: German Democratic Republic (historic) | E110: German Dem. Rep | F110: German Democratic Republic (historic) | G110: German Democratic Republic (historic) | H110: German Democratic Republic (historic) | K110: : | L110: : | M110: : | N110: : | O110: : | P110: : | Q110: :
A111: DE | B111: DEU | C111: Germany | D111: 004 | E111: Germany | F111: Germany | G111: Germany | H111: Germany | I111: 276 | J111: 276 | K111: 79 | L111: DE | M111: EU27 | N111: DE | O111: DE | P111: EU27 | Q111: _i | R111: ^(?!e|w)(fed)?.*germany(?!,? *e|,? *w)(,? *)(\bfed)?
A112: DJ | B112: DJI | C112: Djibouti | F112: Djibouti | G112: Djibouti | H112: Djibouti | I112: 262 | J112: 262 | K112: 72 | L112: RoW | M112: WN | N112: WX | O112: WX | P112: WX | Q112: _e | R112: djibouti
A113: DK | B113: DNK | C113: Denmark | D113: 008 | E113: Denmark | F113: Denmark | G113: Denmark | H113: Denmark | I113: 208 | J113: 208 | K113: 54 | L113: DK | M113: EU27 | N113: DK | O113: DK | P113: EU27 | Q113: _i | R113: denmark
A114: DM | B114: DMA | C114: Dominica | F114: Dominica | G114: Dominica | H114: Dominica | J114: 212 | K114: 55 | L114: RoW | M114: WN | N114: WX | O114: WX | P114: WX | Q114: _e | R114: dominica(?!n)
A115: DO | B115: DOM | C115: Dominican Republic | E115: Dominican Republic | F115: Dominican Republic | G115: Dominican Republic | H115: Dominican Republic | I115: 214 | J115: 214 | K115: 56 | L115: RoW | M115: WN | N115: WX | O115: WX | P115: WX | Q115: _e | R115: dominican
A116: DZ | B116: DZA | C116: Algeria | E116: Algeria | F116: Algeria | G116: Algeria | H116: Algeria | I116: 012 | J116: 12 | K116: 4 | L116: RoW | M116: WN | N116: WX | O116: WX | P116: WX | Q116: _e | R116: algeria
A117: EAZ | B117: EAZ | C117: Zanzibar (historic) | F117: Zanzibar (historic) | G117: Zanzibar (historic) | H117: Zanzibar (historic) | K117: : | L117: : | M117: : | N117: : | O117: : | P117: : | Q117: :
A118: EC | B118: ECU | C118: Ecuador | E118: Ecuador | F118: Ecuador | G118: Ecuador | H118: Ecuador | I118: 218 | J118: 218 | K118: 58 | L118: RoW | M118: WN | N118: WX | O118: WX | P118: WX | Q118: _e | R118: ecuador
A119: EE | B119: EST | C119: Estonia | D119: 053 | E119: Estonia | F119: Estonia | G119: Estonia | H119: Estonia | I119: 233 | J119: 233 | K119: 63 | L119: EE | M119: EU27 | N119: EE | O119: EE | P119: EU27 | Q119: _i | R119: estonia
A120: EG | B120: EGY | C120: Egypt | E120: Egypt | F120: Egypt | G120: Egypt | H120: Egypt | I120: 818 | J120: 818 | K120: 59 | L120: RoW | M120: WN | N120: WX | O120: WX | P120: WX | Q120: _e | R120: egypt
A121: EH | B121: ESH | C121: Western Sahara | F121: Western Sahara | G121: Western Sahara | H121: Western Sahara | K121: 205 | L121: RoW | M121: WN | N121: WX | O121: WX | P121: WX | Q121: _e | R121: \bw.*sahara
...

Sheet ieap
A2: ieap | B2: rmh | C2: rm | D2: mfa | E2: ieap_label | F2: rmh_label | G2: mfa_label | H2: nrgp | I2: nrgp_label
A3: BIOFUEL_NONSPEC | B3: : | C3: : | D3: : | E3: Non-specified primary biofuels & waste | F3: =VLOOKUP([1]ieap!B3,[1]rmh!A$4:B$197,2,FALSE) -> : | H3: BIOE | I3: Bioenergy
A4: HARDCOAL_ND | B4: RM021 | C4: RM021 | D4: : | E4: Hard coal (no detail) | F4: =VLOOKUP([1]ieap!B4,[1]rmh!A$4:B$197,2,FALSE) -> Hard coal | H4: C0100 | I4: Hard coal
A5: ANTHRACITE | B5: RM021 | C5: RM021 | D5: MF412 | E5: Anthracite | F5: =VLOOKUP([1]ieap!B5,[1]rmh!A$4:B$197,2,FALSE) -> Hard coal | H5: C0110 | I5: Anthracite
A6: COKING_COAL | B6: RM021 | C6: RM021 | D6: MF412 | E6: Coking coal | F6: =VLOOKUP([1]ieap!B6,[1]rmh!A$4:B$197,2,FALSE) -> Hard coal | H6: C0121 | I6: Coking coal
A7: OTH_BITCOAL | B7: RM021 | C7: RM021 | D7: MF412 | E7: Other bituminous coal | F7: =VLOOKUP([1]ieap!B7,[1]rmh!A$4:B$197,2,FALSE) -> Hard coal | H7: C0129 | I7: Other bituminous coal
A8: BROWNCOAL_ND | B8: RM022 | C8: RM022 | D8: : | E8: Brown coal (no detail) | F8: =VLOOKUP([1]ieap!B8,[1]rmh!A$4:B$197,2,FALSE) -> Lignite | H8: C0200 | I8: Brown coal
A9: SUB_BITCOAL | B9: RM022 | C9: RM022 | D9: MF411 | E9: Sub-bituminous coal | F9: =VLOOKUP([1]ieap!B9,[1]rmh!A$4:B$197,2,FALSE) -> Lignite | H9: C0210 | I9: Sub-bituminous coal | K9: ieap rm RM022 but linked nrgp C0210 has rm RM021
A10: LIGNITE | B10: RM022 | C10: RM022 | D10: MF411 | E10: Lignite | F10: =VLOOKUP([1]ieap!B10,[1]rmh!A$4:B$197,2,FALSE) -> Lignite | H10: C0220 | I10: Lignite
A11: COKE_OVEN_COKE_OTH | B11: RM066 | C11: RM066 | D11: MF412 | E11: Coke oven cokes | F11: =VLOOKUP([1]ieap!B11,[1]rmh!A$4:B$197,2,FALSE) -> Coke oven products | H11: C0311 | I11: Coke oven coke
A12: GAS_COKE | B12: RM066 | C12: RM066 | D12: MF412 | E12: Gas Coke | F12: =VLOOKUP([1]ieap!B12,[1]rmh!A$4:B$197,2,FALSE) -> Coke oven products | H12: C0312 | I12: Gas coke
A13: PATENT_FUEL | B13: RM067.1 | C13: RM067 | D13: MF412 | E13: Patent fuel | F13: =VLOOKUP([1]ieap!B13,[1]rmh!A$4:B$197,2,FALSE) -> Briquettes and patent fuel | H13: C0320 | I13: Patent fuel
A14: BKB | B14: RM067.1 | C14: RM067 | D14: MF411 | E14: Brown coal briquettes (BKB) | F14: =VLOOKUP([1]ieap!B14,[1]rmh!A$4:B$197,2,FALSE) -> Briquettes and patent fuel | H14: C0330 | I14: Brown coal briquettes
A15: COAL_TAR | B15: RM066 | C15: RM066 | D15: MF412 | E15: Coal tar | F15: =VLOOKUP([1]ieap!B15,[1]rmh!A$4:B$197,2,FALSE) -> Coke oven products | H15: C0340 | I15: Coal tar
A16: COKE_OVEN_GAS | B16: RM066 | C16: RM066 | D16: MF412 | E16: Coke oven gas | F16: =VLOOKUP([1]ieap!B16,[1]rmh!A$4:B$197,2,FALSE) -> Coke oven products | H16: C0350 | I16: Coke oven gas
A17: MANUFACTURED_GAS_OUTPUT | B17: : | C17: : | D17: : | E17: Elec/heat output from non-specified manufactured gases | F17: =VLOOKUP([1]ieap!B17,[1]rmh!A$4:B$197,2,FALSE) -> : | H17: C0350-0370 | I17: Manufactured gases
A18: GASWORKS_GAS | B18: RM125.1 | C18: RM125 | D18: : | E18: Gas works gas | F18: =VLOOKUP([1]ieap!B18,[1]rmh!A$4:B$197,2,FALSE) -> Gas supply | H18: C0360 | I18: Gas works gas | K18: link nrgp is blank
A19: BLAST_FURNACE_GAS | B19: : | C19: : | D19: : | E19: Blast furnace gas | F19: =VLOOKUP([1]ieap!B19,[1]rmh!A$4:B$197,2,FALSE) -> : | H19: C0371 | I19: Blast furnace gas
A20: OTH_RECOVGASES | B20: : | C20: : | D20: : | E20: Other recovered gases | F20: =VLOOKUP([1]ieap!B20,[1]rmh!A$4:B$197,2,FALSE) -> : | H20: C0379 | I20: Other recovered gases
A21: ELECTRICITY | B21: RM124.1 | C21: RM124 | D21: Waste | E21: Electricity | F21: =VLOOKUP([1]ieap!B21,[1]rmh!A$4:B$197,2,FALSE) -> Electricity supply | H21: E7000 | I21: Electricity
A22: NATURAL_GAS | B22: RM025 | C22: RM025 | D22: MF422 | E22: Natural Gas | F22: =VLOOKUP([1]ieap!B22,[1]rmh!A$4:B$197,2,FALSE) -> Natural gas | H22: G3000 | I22: Natural gas
A23: HEAT | B23: RM126.1 | C23: RM126 | D23: Waste | E23: Heat | F23: =VLOOKUP([1]ieap!B23,[1]rmh!A$4:B$197,2,FALSE) -> Steam, air conditioning | H23: H8000 | I23: Heat
A24: HEAT_COMBUSTIBLES_NS | B24: RM126.1 | C24: RM126 | D24: Waste | E24: Heat production from non-specified combustible fuels | F24: =VLOOKUP([1]ieap!B24,[1]rmh!A$4:B$197,2,FALSE) -> Steam, air conditioning | H24: H8000 | I24: Heat
A25: NUCLEAR | B25: RM098 | C25: RM098 | D25: MF228 | E25: Nuclear | F25: =VLOOKUP([1]ieap!B25,[1]rmh!A$4:B$197,2,FALSE) -> Nuclear fuel/heat | H25: N900H | I25: Nuclear heat
A26: CRUDE_OIL | B26: RM023 | C26: RM023 | D26: MF421 | E26: Crude oil | F26: =VLOOKUP([1]ieap!B26,[1]rmh!A$4:B$197,2,FALSE) -> Petroleum oils | H26: O4100_TOT | I26: Crude oil
A27: OIL_PRIM_PRODUCTS_ND | B27: : | C27: : | D27: : | E27: Primary oil (no detail) | F27: =VLOOKUP([1]ieap!B27,[1]rmh!A$4:B$197,2,FALSE) -> : | H27: O4100_TOT_4200-4500 | I27: Crude oil, NGL, refinery feedstocks, additives and oxygenates and other hydrocarbons
A28: NGL | B28: RM023 | C28: RM023 | D28: MF421 | E28: Natural gas liquids | F28: =VLOOKUP([1]ieap!B28,[1]rmh!A$4:B$197,2,FALSE) -> Petroleum oils | H28: O4200 | I28: Natural gas liquids
A29: REFINERY_FEEDSTOCKS | B29: RM067.6 | C29: RM067 | D29: MF421 | E29: Refinery feedstocks | F29: =VLOOKUP([1]ieap!B29,[1]rmh!A$4:B$197,2,FALSE) -> Other petroleum products | H29: O4300 | I29: Refinery feedstocks
A30: ADDITIVES | B30: RM067.6 | C30: RM067 | D30: : | E30: Additives/blending component | F30: =VLOOKUP([1]ieap!B30,[1]rmh!A$4:B$197,2,FALSE) -> Other petroleum products | H30: O4400 | I30: Additives and oxygenates
... A70: OTH_ENSOURC | B70: : | C70: : | D70: : | E70: Other energy sources | F70: =VLOOKUP([1]ieap!B70,[1]rmh!A$4:B$197,2,FALSE) -> : | H70: X9900 | I70: Other fuels n.e.c.

Sheet nrg
B1: Can you please try to map this to the rhm classification (see sheet for iea data)?
A2: nrg | B2: ind | C2: rmh | D2: rm | E2: rme | F2: cpa28 | G2: nrg_label | H2: remark
A3: AFC | B3: : | C3: : | D3: : | E3: : | G3: Available for final consumption
A4: DL | B4: 35.1 | C4: : | D4: : | E4: RME141 | G4: Distribution losses
A5: EXP | B5: EXP | C5: EXP | D5: EXP | E5: EXP | G5: Exports
A6: FC_E | B6: : | C6: : | D6: : | E6: : | G6: Final consumption - energy use
A7: FC_IND_CON_E | B7: 41, 42, 43 | C7: RM129 | D7: : | E7: RME146 | G7: Final consumption - industry sector - construction - energy use
A8: FC_IND_CPC_E | B8: A 20, 21 | C8: RM068-076 | D8: : | E8: RME077-085 | G8: Final consumption - industry sector - chemical and petrochemical - energy use
A9: FC_IND_E | B9: : | C9: : | D9: : | E9: : | G9: Final consumption - industry sector - energy use
A10: FC_IND_FBT_E | B10: 10, 11, 12 | C10: RM049-058 | D10: : | E10: RME057-067 | G10: Final consumption - industry sector - food, beverages and tobacco - energy use
A11: FC_IND_IS_E | B11: 24.1, 24.2, 24.3, 24.51, 24.52 | C11: RM087_099 | D11: : | E11: RME096_114_115 | G11: Final consumption - industry sector - iron and steel - energy use
A12: FC_IND_MAC_E | B12: 25, 26, 27, 28 | C12: RM101-110 | D12: : | E12: RME118-127 | G12: Final consumption - industry sector - machinery - energy use
A13: FC_IND_MQ_E | B13: 07, 08, 09.9 | C13: RM026-048 | D13: : | E13: RME027-056 | G13: Final consumption - industry sector - mining and quarrying - energy use
A14: FC_IND_NE | B14: : | C14: : | D14: : | E14: : | G14: Final consumption - industry sector - non-energy use
A15: FC_IND_NFM_E | B15: 24.4, 24.53, 24.54 | C15: RM088-098 | D15: : | E15: RME097-112_116_117 | G15: Final consumption - industry sector - non-ferrous metals - energy use
A16: FC_IND_NMM_E | B16: 23 | C16: RM079-086 | D16: : | E16: RME088-095 | G16: Final consumption - industry sector - non-metallic minerals - energy use
A17: FC_IND_NSP_E | B17: 22, 31, 32 | C17: : | D17: : | E17: RME086_087_133-139 | G17: Final consumption - industry sector - not elsewhere specified - energy use
A18: FC_IND_PPP_E | B18: 17, 18 | C18: RM063-065 | D18: : | E18: RME072-074 | G18: Final consumption - industry sector - paper, pulp and printing - energy use
A19: FC_IND_TE_E | B19: 29, 30 | C19: RM111-115 | D19: : | E19: RME128-132 | G19: Final consumption - industry sector - transport equipment - energy use
A20: FC_IND_TL_E | B20: 13, 14, 15 | C20: RM059-061 | D20: : | E20: RME068-070 | G20: Final consumption - industry sector - textile and leather - energy use
A21: FC_IND_WP_E | B21: 16 | C21: RM062 | D21: : | E21: RME071 | G21: Final consumption - industry sector - wood and wood products - energy use
A22: FC_NE | B22: A 20, 21 | C22: : | D22: : | E22: : | G22: Final consumption - non-energy use
A23: FC_OTH_AF_E | B23: 01, 02 | C23: RM001-018_019.1-019.2 | D23: : | E23: RME001-020 | G23: Final consumption - other sectors - agriculture and forestry - energy use
A24: FC_OTH_CP_E | B24: 33, 36, 37, 38, 39, 45, 46, 47, 52, 53, 55, 56, 58, 59, 60, 61, 62, 63, 64, 65, 66, 68, 69, 70, 71, 72, 73, 74, 75, 77, 78, 79, 80, 81, 82, 84 (excluding Class 8422), 85, 86, 87, 88, 90, 91, 92, 93, 94, 95, 96 and 99 | C24: RM123_127-128.2_130-132_136-164_166 | D24: : | E24: RME140-182nec | G24: Final consumption - other sectors - commercial and public services - energy use
A25: FC_OTH_E | B25: : | C25: : | D25: : | E25: : | G25: Final consumption - other sectors - energy use
A26: FC_OTH_FISH_E | B26: 03 | C26: RM020 | D26: : | E26: RME021 | G26: Final consumption - other sectors - fishing - energy use
A27: FC_OTH_HH_E | B27: HFCE | C27: HFCE | D27: : | E27: HFCE | G27: Final consumption - other sectors - households - energy use
A28: FC_OTH_NE | B28: : | C28: : | D28: : | E28: RME140-182nec | G28: Final consumption - other sectors - non-energy use | H28: w/o 41-43(RME146) construction
A29: FC_OTH_NSP_E | B29: 84 | C29: RM156 | D29: : | E29: RME173 | G29: Final consumption - other sectors - not elsewhere specified - energy use
A30: FC_TRA_DAVI_E | B30: 51 | C30: RM135 | D30: : | E30: RME152 | G30: Final consumption - transport sector - domestic aviation - energy use
A31: FC_TRA_DNAVI_E | B31: 50 | C31: RM134 | D31: : | E31: RME151 | G31: Final consumption - transport sector - domestic navigation - energy use
A32: FC_TRA_E | B32: : | C32: : | D32: : | E32: : | G32: Final consumption - transport sector - energy use
A33: FC_TRA_NE | B33: : | C33: RM133 | D33: : | E33: RME150 | G33: Final consumption - transport sector - non-energy use
A34: FC_TRA_NSP_E | B34: 49.3, 49.4, 49.5 | C34: RM133 | D34: : | E34: RME150 | G34: Final consumption - transport sector - not elsewhere specified - energy use
A35: FC_TRA_PIPE_E | B35: 49.3, 49.4, 49.5 | C35: RM133 | D35: : | E35: RME150 | G35: Final consumption - transport sector - pipeline transport - energy use
A36: FC_TRA_RAIL_E | B36: 49.1, 49.2 | C36: RM133 | D36: : | E36: RME150 | G36: Final consumption - transport sector - rail - energy use
A37: FC_TRA_ROAD_E | B37: 49.3, 49.4, 49.5 | C37: RM133 | D37: : | E37: xRME150_HFCE | G37: Final consumption - transport sector - road - energy use | H37: 36 % of diesel oil and 95 % of gasoline is allocated to household consumption, the remainder to RME150 Land transport
A38: FEC2020-2030 | B38: : | C38: : | D38: : | E38: : | G38: Final energy consumption (Europe 2020-2030)
A39: GAE | B39: : | C39: : | D39: : | E39: : | G39: Gross available energy
A40: GEP | B40: : | C40: : | D40: : | E40: : | G40: Gross electricity production
A41: GEP_APCHP | B41: : | C41: : | D41: : | E41: : | G41: Gross electricity production - main activity producer electricity only
A42: GEP_APE | B42: : | C42: : | D42: : | E42: : | G42: Gross electricity production - main activity producer combined heat and power
A43: GEP_MAPCHP | B43: : | C43: : | D43: : | E43: : | G43: Gross electricity production - autoproducer electricity only
A44: GEP_MAPE | B44: : | C44: : | D44: : | E44: : | G44: Gross electricity production - autoproducer combined heat and power
A45: GHP | B45: : | C45: : | D45: : | E45: : | G45: Gross heat production
A46: GHP_APCHP | B46: : | C46: : | D46: : | E46: : | G46: Gross heat production - main activity producer combined heat and power
A47: GHP_APH | B47: : | C47: : | D47: : | E47: : | G47: Gross heat production - main activity producer heat only
A48: GHP_MAPCHP | B48: : | C48: : | D48: : | E48: : | G48: Gross heat production - autoproducer combined heat and power
A49: GHP_MAPH | B49: : | C49: : | D49: : | E49: : | G49: Gross heat production - autoproducer heat only
... A52: IMP | B52: IMP | C52: IMP | D52: IMP | E52: IMP | G52: Imports
A53: INTAVI | B53: BUNKAV | C53: EXP | D53: EXP | E53: EXP | G53: International aviation | H53: Karl: International bunkers according to the energy balance are allocated to exports. Bunkers according to EW-MFA are additionally added to imports, exports and domestic use.
A54: INTMARB | B54: BUNKNAV | C54: EXP | D54: EXP | E54: EXP | G54: International maritime bunkers
A55: NRG_BF_E | B55: 24.1, 24.2, 24.3, 24.51, 24.52 | C55: RM087_099 | D55: : | E55: RME096_114_115 | G55: Energy sector - blast furnaces - energy use
A56: NRG_BIOG_E | B56: 35.2 | C56: RM068-076 | D56: : | E56: RME142 | G56: Energy sector - gasification plants for biogas - energy use
A57: NRG_BKBPB_E | B57: 19.2 | C57: RM067.1 | D57: : | E57: RME076 | G57: Energy sector - brown coal briquettes and peat briquettes plants - energy use
A58: NRG_CL_E | B58: 19.2 | C58: RM067.1-067.6 | D58: : | E58: RME076 | G58: Energy sector - coal liquefaction plants - energy use
A59: NRG_CM_E | B59: 05 | C59: RM021-022 | D59: : | E59: RME022-023 | G59: Energy sector - coal mines - energy use
A60: NRG_CO_E | B60: 19.1 | C60: RM066 | D60: : | E60: RME075 | G60: Energy sector - coke ovens - energy use
A61: NRG_CPP_E | B61: 19.2 | C61: RM067.1-067.6 | D61: : | E61: RME076 | G61: Energy sector - charcoal production plants - energy use
A62: NRG_E | B62: : | C62: : | D62: : | E62: : | G62: Energy sector - energy use
A63: NRG_EHG_E | B63: 35.1 | C63: RM124.1 | D63: : | E63: RME141 | G63: Energy sector - electricity and heat generation - energy use
A64: NRG_GTL_E | B64: 19.2 | C64: RM067.1-067.6 | D64: : | E64: RME076 | G64: Energy sector - gas-to-liquids plants - energy use
A65: NRG_GW_E | B65: 35.2 | C65: RM125.1 | D65: : | E65: RME142 | G65: Energy sector - gas works - energy use
A66: NRG_LNG_E | B66: 19.2 | C66: RM067.1-067.6 | D66: : | E66: RME076 | G66: Energy sector - liquefaction and regasification plants (LNG) - energy use
A67: NRG_NE | B67: : | C67: : | D67: : | E67: : | G67: Energy sector - non-energy use
A68: NRG_NI_E | B68: 24.4, 24.53, 24.54 | C68: RM098 | D68: : | E68: RME113 | G68: Energy sector - nuclear industry - energy use | H68: change compared to Karl who assigned it to other metals
A69: NRG_NSP_E | B69: 35.1 | C69: xRM067.1-067.6_RM124.1 | D69: : | E69: RME141 | G69: Energy sector - not elsewhere specified - energy use
A70: NRG_OIL_NG_E | B70: 06 | C70: RM023-025 | D70: : | E70: RME024-026 | G70: Energy sector - oil and natural gas extraction plants - energy use
A71: NRG_PF_E | B71: 19.2 | C71: RM067.1 | D71: : | E71: RME076 | G71: Energy sector - patent fuel plants - energy use
A72: NRG_PR_E | B72: 19.2 | C72: RM067.1-067.6 | D72: : | E72: RME076 | G72: Energy sector - petroleum refineries (oil refineries) - energy use
A73: NRGSUP | B73: : | C73: : | D73: : | E73: : | G73: Total energy supply
A74: PEC2020-2030 | B74: : | C74: : | D74: : | E74: : | G74: Primary energy consumption (Europe 2020-2030)
A75: PPRD | B75: OUT | C75: OUT | D75: OUT | E75: OUT | G75: Primary production
A76: RCV_RCY | B76: OUT | C76: : | D76: OUT | E76: OUT | G76: Recovered and recycled products
A77: STATDIFF | B77: : | C77: CINV | D77: minus_OUT | E77: -OUT | G77: Statistical differences
A78: STK_CHG | B78: CHINV | C78: CINV | D78: : | E78: -CINV | G78: Change in stock
A79: TI_BF_E | B79: 24.1, 24.2, 24.3, 24.51, 24.52 | C79: RM087_099 | D79: : | E79: RME096_114_115 | G79: Transformation input - blast furnaces - energy use
A80: TI_BKBPB_E | B80: 19.2 | C80: RM067.1 | D80: : | E80: RME076 | G80: Transformation input - brown coal briquettes and peat briquettes plants - energy use
A81: TI_BNG_E | B81: 35.2 | C81: RM125.1 | D81: : | E81: RME142 | G81: Transformation input - for blended natural gas - energy use
A82: TI_CL_E | B82: 19.2 | C82: RM067.1-067.6 | D82: : | E82: RME076 | G82: Transformation input - coal liquefaction plants - energy use
A83: TI_CO_E | B83: 19.1 | C83: RM066 | D83: : | E83: RME075 | G83: Transformation input - coke ovens - energy use
A84: TI_CPP_E | B84: 19.2 | C84: RM067.1-067.6 | D84: : | E84: RME076 | G84: Transformation input - charcoal production plants - energy use
A85: TI_E | B85: : | C85: : | D85: : | E85: : | G85: Transformation input - energy use
A86: TI_EHG_APCHP_E | B86: x35.1_35.3 | C86: xRM124.1_RM126.1 | D86: : | E86: xRME141_143 | G86: Transformation input - electricity and heat generation - autoproducer combined heat and power - energy use | H86: split later: 67% to 35.1, 33% to 35.3
A87: TI_EHG_APE_E | B87: 35.1 | C87: RM124.1 | D87: : | E87: RME141 | G87: Transformation input - electricity and heat generation - autoproducer electricity only - energy use
A88: TI_EHG_APH_E | B88: 35.3 | C88: RM126.1 | D88: : | E88: RME143 | G88: Transformation input - electricity and heat generation - autoproducer heat only - energy use
A89: TI_EHG_DHEP | B89: 35.1 | C89: RM124.1 | D89: : | E89: RME141 | G89: Transformation input - electricity and heat generation - derived heat for electricity production
A90: TI_EHG_CB | B90: 35.1 | C90: : | D90: : | E90: RME141 | G90: Transformation input - electricity and heat generation - charging batteries | H90: allocation to electricity, new item, 16.02.2024, correkt?
A91: TI_EHG_E | B91: : | C91: : | D91: : | E91: : | G91: Transformation input - electricity and heat generation - energy use
A92: TI_EHG_EB | B92: 35.3 | C92: RM124.1 | D92: : | E92: RME143 | G92: Transformation input - electricity and heat generation - electric boilers
A93: TI_EHG_EDHP | B93: 35.3 | C93: RM126.4 | D93: : | E93: RME143 | G93: Transformation input - electricity and heat generation - electrically driven heat pumps
A94: TI_EHG_EPS | B94: 35.1 | C94: : | D94: : | E94: RME141 | G94: Transformation input - electricity and heat generation - electricity for pumped storage
A95: TI_EHG_MAPCHP_E | B95: x35.1_35.3 | C95: xRM124.1_RM126.1 | D95: : | E95: xRME141_143 | G95: Transformation input - electricity and heat generation - main activity producer combined heat and power - energy use | H95: split later: 67% to 35.1, 33% to 35.3
A96: TI_EHG_MAPE_E | B96: 35.1 | C96: RM124.1 | D96: : | E96: RME141 | G96: Transformation input - electricity and heat generation - main activity producer electricity only - energy use
A97: TI_EHG_MAPH_E | B97: 35.3 | C97: RM126.1 | D97: : | E97: RME143 | G97: Transformation input - electricity and heat generation - main activity producer heat only - energy use
A98: TI_GTL_E | B98: 19.2 | C98: RM067.1-067.6 | D98: : | E98: RME076 | G98: Transformation input - gas-to-liquids plants - energy use
A99: TI_GW_E | B99: 35.2 | C99: RM125.1 | D99: : | E99: RME142 | G99: Transformation input - gas works - energy use
A100: TI_LBB_E | B100: 19.2 | C100: : | D100: : | E100: RME076 | G100: Transformation input - liquid biofuels blended - energy use
A101: TI_NE | B101: : | C101: : | D101: : | E101: : | G101: Transformation input - non-energy use
A102: TI_NRG_FC_IND_NE | B102: : | C102: xRM067.1-067.6_RM124.1 | D102: : | E102: xRME076_141 | G102: Transformation input, energy sector and final consumption in industry sector - non-energy use | H102: 50% RME076, 50% RME141
...

Sheet iea
A2: iea | B2: rmh | C2: iea_label | D2: cpa28 | E2: rmh_label | F2: cpa | G2: nrg | H2: nrg_label
A3: AGRI_FOREST | B3: RM001-018_019.1-019.2 | C3: Agriculture and forestry | D3: 01-02 | E3: =IFERROR(VLOOKUP(B3,[1]rmh!$A$3:$B$196,2,FALSE),"") | G3: FC_OTH_AF_E | H3: Final consumption - other sectors - agriculture and forestry - energy use
A4: AUTOCHP | B4: 67% RM124.1, 33% RM126.1 | C4: Autoproducer CHP plants | D4: 67% 35.1, 33 % 35.3 | E4: =IFERROR(VLOOKUP(B4,[1]rmh!$A$3:$B$196,2,FALSE),"") | G4: TI_EHG_APCHP_E | H4: Transformation input - electricity and heat generation - autoproducer combined heat and power - energy use
A5: AUTOELEC | B5: RM124.1 | C5: Autoproducer electricity plants | D5: 35.1 | E5: =IFERROR(VLOOKUP(B5,[1]rmh!$A$3:$B$196,2,FALSE),"") -> Electricity supply | G5: TI_EHG_APE_E | H5: Transformation input - electricity and heat generation - autoproducer electricity only - energy use
A6: AUTOHEAT | B6: RM126.1 | C6: Autoproducer heat plants | D6: 35.3 | E6: =IFERROR(VLOOKUP(B6,[1]rmh!$A$3:$B$196,2,FALSE),"") -> Steam, air conditioning | G6: TI_EHG_APH_E | H6: Transformation input - electricity and heat generation - autoproducer heat only - energy use
A7: BUNKERS_AVIATION | B7: EXP | C7: International aviation bunkers | D7: BUNKAV | E7: =IFERROR(VLOOKUP(B7,[1]rmh!$A$3:$B$196,2,FALSE),"") -> Exports | G7: INTAVI | H7: International aviation
A8: BUNKERS_MARINE | B8: EXP | C8: International marine bunkers | D8: BUNKNAV | E8: =IFERROR(VLOOKUP(B8,[1]rmh!$A$3:$B$196,2,FALSE),"") -> Exports | G8: INTMARB | H8: International maritime bunkers
A9: CHEMICAL | B9: RM068-076 | C9: Chemical and Petrochemical | D9: 20,21 | E9: =IFERROR(VLOOKUP(B9,[1]rmh!$A$3:$B$196,2,FALSE),"") | G9: FC_IND_CPC_E | H9: Final consumption - industry sector - chemical and petrochemical - energy use
A10: COMMPUB | B10: RM123_127-128.2_130-132_136-164_166 | C10: Commercial and public services | D10: 33, 36-39, 45-47, 52, 53, 55, 56, 58, 59, 60, 61, 62, 63, 64, 65, 66, 68, 69, 70, 71, 72, 73, 74, 75, 77, 78, 79, 80, 81, 82, 84 (excluding Class 8422), 85, 86, 87, 88, 90, 91, 92, 93, 94, 95, 96 and 99 | E10: =IFERROR(VLOOKUP(B10,[1]rmh!$A$3:$B$196,2,FALSE),"") | G10: FC_OTH_CP_E | H10: Final consumption - other sectors - commercial and public services - energy use
A11: CONSTRUC | B11: RM129 | C11: Construction | D11: 41-43 | E11: =IFERROR(VLOOKUP(B11,[1]rmh!$A$3:$B$196,2,FALSE),"") -> Construction | G11: FC_IND_CON_E | H11: Final consumption - industry sector - construction - energy use
A12: DISTLOSS | B12: : | C12: Distribution losses | D12: : | E12: =IFERROR(VLOOKUP(B12,[1]rmh!$A$3:$B$196,2,FALSE),"") | G12: DL | H12: Distribution losses
A13: DOMESAIR | B13: RM135 | C13: Domestic aviation | D13: 51 | E13: =IFERROR(VLOOKUP(B13,[1]rmh!$A$3:$B$196,2,FALSE),"") -> Air transport | G13: FC_TRA_DAVI_E | H13: Final consumption - transport sector - domestic aviation - energy use
A14: DOMESNAV | B14: RM134 | C14: Domestic navigation | D14: 50 | E14: =IFERROR(VLOOKUP(B14,[1]rmh!$A$3:$B$196,2,FALSE),"") -> Water transport | G14: FC_TRA_DNAVI_E | H14: Final consumption - transport sector - domestic navigation - energy use
... A52: MAINHEAT | B52: RM126.1 | C52: Main activity producer heat plants | D52: 35.3 | E52: =IFERROR(VLOOKUP(B52,[1]rmh!$A$3:$B$196,2,FALSE),"") -> Steam, air conditioning | G52: TI_EHG_MAPH_E | H52: Transformation input - electricity and heat generation - main activity producer heat only - energy use
A53: MANUFACT | B53: : | C53: Manufacturing | D53: : | E53: =IFERROR(VLOOKUP(B53,[1]rmh!$A$3:$B$196,2,FALSE),"")
A54: MINING | B54: RM026-048 | C54: Mining and Quarrying (excluding energy products) | D54: 07, 08, 09.9 | E54: =IFERROR(VLOOKUP(B54,[1]rmh!$A$3:$B$196,2,FALSE),"") | G54: FC_IND_MQ_E | H54: Final consumption - industry sector - mining and quarrying - energy use
A55: NE_CHEM | B55: RM068-076 | C55: Non-energy use - chemical/petrochemical | D55: 20-21 | E55: =IFERROR(VLOOKUP(B55,[1]rmh!$A$3:$B$196,2,FALSE),"") | G55: FC_IND_NE | H55: Final consumption - industry sector - non-energy use
A56: NE_CONSTRUC | B56: RM129 | C56: Non-energy use in construction | D56: 41-43 | E56: =IFERROR(VLOOKUP(B56,[1]rmh!$A$3:$B$196,2,FALSE),"") -> Construction | G56: FC_IND_NE | H56: Final consumption - industry sector - non-energy use
A57: NE_FOODPRO | B57: RM049-058 | C57: Non-energy use in food/beverages/tobacco | D57: 10-12 | E57: =IFERROR(VLOOKUP(B57,[1]rmh!$A$3:$B$196,2,FALSE),"") | G57: FC_IND_NE | H57: Final consumption - industry sector - non-energy use
A58: NE_IND | B58: : | C58: Non-energy use in Industry | D58: : | E58: =IFERROR(VLOOKUP(B58,[1]rmh!$A$3:$B$196,2,FALSE),"") | G58: FC_IND_NE | H58: Final consumption - industry sector - non-energy use
A59: NE_IND_TRANSF | B59: 50% RM067.1-RM067.6, 50% RM124.1 | C59: Non-energy use in Industry/Transformation/Energy | D59: 50% 19.2, 50% 35.1 | E59: =IFERROR(VLOOKUP(B59,[1]rmh!$A$3:$B$196,2,FALSE),"") | G59: TI_NRG_FC_IND_NE | H59: Transformation input, energy sector and final consumption in industry sector - non-energy use
A60: NE_INONSPEC | B60: : | C60: Non-energy use in industry not elsewhere specified | D60: : | E60: =IFERROR(VLOOKUP(B60,[1]rmh!$A$3:$B$196,2,FALSE),"") | G60: FC_IND_NE | H60: Final consumption - industry sector - non-energy use
A61: NE_IRONSTL | B61: RM087_099 | C61: Non-energy use in Iron and steel | D61: 24.1, 24.2, 24.3, 24.51, 24.52 | E61: =IFERROR(VLOOKUP(B61,[1]rmh!$A$3:$B$196,2,FALSE),"") | G61: FC_IND_NE | H61: Final consumption - industry sector - non-energy use
A62: NE_MACHINE | B62: RM101-110 | C62: Non-energy use in Machinery | D62: 25-28 | E62: =IFERROR(VLOOKUP(B62,[1]rmh!$A$3:$B$196,2,FALSE),"") | G62: FC_IND_NE | H62: Final consumption - industry sector - non-energy use
A63: NE_MINING | B63: RM026-048 | C63: Non-energy use in Mining and quarrying | D63: 07, 08, 09.9 | E63: =IFERROR(VLOOKUP(B63,[1]rmh!$A$3:$B$196,2,FALSE),"") | G63: FC_IND_NE | H63: Final consumption - industry sector - non-energy use
A64: NE_NONFERR | B64: RM088-098 | C64: Non-energy use in Non-ferrous metals | D64: 24.4, 24.53, 24.54 | E64: =IFERROR(VLOOKUP(B64,[1]rmh!$A$3:$B$196,2,FALSE),"") | G64: FC_IND_NE | H64: Final consumption - industry sector - non-energy use
A65: NE_NONMET | B65: RM079-086 | C65: Non-energy use in Non-metallic minerals | D65: 23 | E65: =IFERROR(VLOOKUP(B65,[1]rmh!$A$3:$B$196,2,FALSE),"") | G65: FC_IND_NE | H65: Final consumption - industry sector - non-energy use
... A108: WOODPRO | B108: RM062 | C108: Wood and wood products | D108: 16 | E108: =IFERROR(VLOOKUP(B108,[1]rmh!$A$3:$B$196,2,FALSE),"") -> Wood | G108: FC_IND_WP_E | H108: Final consumption - industry sector - wood and wood products - energy use

Sheet nrgp
A2: nrgp | B2: rm | C2: rme | D2: cpa28 | E2: mfa | F2: nrgp_label | G2: rme_label
A3: BA100 | B3: RM124 | C3: RM124 | E3: Other | F3: Batteries | G3: Electricity, transmission and distribution services | H3: added 18.03.2024 (pyct)
A4: BIOE | B4: : | C4: : | E4: : | F4: Bioenergy
A5: C0000X0350-0370 | B5: : | C5: : | E5: : | F5: Solid fossil fuels
A6: C0100 | B6: : | C6: : | E6: : | F6: Hard coal | H6: aggregate
A7: C0110 | B7: RM021 | C7: RME022 | D7: CPA_B05.1 | E7: MF412 | F7: Anthracite | G7: Hard coal
A8: C0121 | B8: RM021 | C8: RME022 | D8: CPA_B05.1 | E8: MF412 | F8: Coking coal | G8: Hard coal
A9: C0129 | B9: RM021 | C9: RME022 | D9: CPA_B05.1 | E9: MF412 | F9: Other bituminous coal | G9: Hard coal
A10: C0200 | B10: : | C10: : | E10: : | F10: Brown coal | H10: aggregate
A11: C0210 | B11: RM021 | C11: RME022 | D11: CPA_B05.2 | E11: MF411 | F11: Sub-bituminous coal | G11: Hard coal
A12: C0220 | B12: RM022 | C12: RME023 | D12: CPA_B05.2 | E12: MF411 | F12: Lignite | G12: Lignite
A13: C0311 | B13: RM066 | C13: RME075 | D13: CPA_C19.1 | E13: MF412 | F13: Coke oven coke | G13: Coke oven products
A14: C0312 | B14: RM066 | C14: RME075 | D14: CPA_C19.1 | E14: MF412 | F14: Gas coke | G14: Coke oven products
A15: C0320 | B15: RM067 | C15: RME076 | D15: CPA_C19.2 | E15: MF412 | F15: Patent fuel | G15: Refined petroleum products
A16: C0330 | B16: RM067 | C16: RME076 | D16: CPA_C19.2 | E16: MF411 | F16: Brown coal briquettes | G16: Refined petroleum products
A17: C0340 | B17: RM066 | C17: RME075 | D17: CPA_C19.1 | E17: MF412 | F17: Coal tar | G17: Coke oven products
A18: C0350 | B18: RM066 | C18: RME075 | D18: CPA_C19.1 | E18: MF422 | F18: Coke oven gas | G18: Coke oven products
A19: C0350-0370 | B19: : | C19: : | E19: : | F19: Manufactured gases
A20: C0360 | B20: : | C20: : | D20: CPA_D35.2 | E20: MF422 | F20: Gas works gas
A21: C0371 | B21: : | C21: : | E21: MF422 | F21: Blast furnace gas
A22: C0379 | B22: : | C22: : | E22: MF422 | F22: Other recovered gases
A23: E7000 | B23: RM124 | C23: RME141 | D23: CPA_D35.1 | E23: Waste | F23: Electricity | G23: Electricity, transmission and distribution services
A24: FE | B24: : | C24: : | E24: : | F24: Fossil energy
A25: G3000 | B25: RM025 | C25: RME026 | D25: CPA_B06.2 | E25: MF422 | F25: Natural gas | G25: Natural gas, liquefied or in gaseous state
A26: G3200 | B26: : | C26: : | E26: : | F26: Liquified natural gas | H26: sub-aggregate
A27: H8000 | B27: RM126 | C27: RME143 | D27: CPA_D35.3 | E27: Waste | F27: Heat | G27: Steam and air conditioning supply services
A28: N900H | B28: RM098 | C28: RME113 | D28: CPA_C24.46 | E28: MF228 | F28: Nuclear heat | G28: Processed nuclear fuel
A29: O4000 | B29: : | C29: : | E29: : | F29: Oil and petroleum products
A30: O4000XBIO | B30: : | C30: : | E30: : | F30: Oil and petroleum products (excluding biofuel portion)
A31: O4100_TOT | B31: RM023 | C31: RME024 | D31: CPA_B06.10.1 | E31: MF421 | F31: Crude oil | G31: Petroleum oils and oils obtained from bituminous minerals, crude
A32: O4100_TOT_4200-4500 | B32: : | C32: : | E32: : | F32: Crude oil, NGL, refinery feedstocks, additives and oxygenates and other hydrocarbons
A33: O4100_TOT_4200-4500XBIO | B33: : | C33: : | E33: : | F33: Crude oil, NGL, refinery feedstocks, additives and oxygenates and other hydrocarbons (excluding biofuel portion)
A34: O4200 | B34: RM023 | C34: RME024 | D34: CPA_B06.10.1 | E34: MF421 | F34: Natural gas liquids | G34: Petroleum oils and oils obtained from bituminous minerals, crude
A35: O4300 | B35: RM067 | C35: RME076 | D35: CPA_C19.2 | E35: MF421 | F35: Refinery feedstocks | G35: Refined petroleum products
A36: O4400 | B36: : | C36: : | E36: : | F36: Additives and oxygenates
A37: O4400X4410 | B37: RM067 | C37: RME076 | D37: CPA_C19.2 | E37: MF421 | F37: Additives and oxygenates (excluding biofuel portion) | G37: Refined petroleum products
A38: O4500 | B38: RM067 | C38: RME076 | D38: CPA_C19.2 | E38: MF421 | F38: Other hydrocarbons | G38: Refined petroleum products
A39: O4600 | B39: : | C39: : | E39: : | F39: Oil products
A40: O4600XBIO | B40: : | C40: : | E40: ; | F40: Oil products (excluding biofuel portion)
A41: O4610 | B41: RM067 | C41: RME076 | D41: CPA_C19.2 | E41: MF421 | F41: Refinery gas | G41: Refined petroleum products
A42: O4620 | B42: RM067 | C42: RME076 | D42: CPA_C19.2 | E42: MF421 | F42: Ethane | G42: Refined petroleum products
A43: O4630 | B43: RM067 | C43: RME076 | D43: CPA_C19.2 | E43: MF421 | F43: Liquefied petroleum gases | G43: Refined petroleum products
A44: O4640 | B44: RM067 | C44: RME076 | D44: CPA_C19.2 | E44: MF421 | F44: Naphtha | G44: Refined petroleum products
A45: O4651 | B45: RM067 | C45: RME076 | D45: CPA_C19.2 | E45: MF421 | F45: Aviation gasoline | G45: Refined petroleum products
A46: O4652 | B46: : | C46: : | E46: : | F46: Motor gasoline
A47: O4652XR5210B | B47: RM067 | C47: RME076 | D47: CPA_C19.2 | E47: MF421 | F47: Motor gasoline (excluding biofuel portion) | G47: Refined petroleum products
A48: O4653 | B48: RM067 | C48: RME076 | D48: CPA_C19.2 | E48: MF421 | F48: Gasoline-type jet fuel | G48: Refined petroleum products
A49: O4661 | B49: : | C49: : | E49: : | F49: Kerosene-type jet fuel
A50: O4661XR5230B | B50: RM067 | C50: RME076 | D50: CPA_C19.2 | E50: MF421 | F50: Kerosene-type jet fuel (excluding biofuel portion) | G50: Refined petroleum products
A51: O4669 | B51: RM067 | C51: RME076 | D51: CPA_C19.2 | E51: MF421 | F51: Other kerosene | G51: Refined petroleum products
A52: O4671 | B52: : | C52: : | E52: : | F52: Gas oil and diesel oil
A53: O46711 | B53: : | C53: : | E53: : | F53: Road diesel
A54: O46712 | B54: : | C54: : | E54: : | F54: Heating and other gasoil
A55: O4671XR5220B | B55: RM067 | C55: RME076 | D55: CPA_C19.2 | E55: MF421 | F55: Gas oil and diesel oil (excluding biofuel portion) | G55: Refined petroleum products
A56: O4680 | B56: RM067 | C56: RME076 | D56: CPA_C19.2 | E56: MF421 | F56: Fuel oil | G56: Refined petroleum products
A57: O4681 | B57: : | C57: : | E57: : | F57: Fuel oil (low sulphur <1%)
A58: O4682 | B58: : | C58: : | E58: : | F58: Fuel oil (high sulphur >=1%)
A59: O4691 | B59: RM067 | C59: RME076 | D59: CPA_C19.2 | E59: MF421 | F59: White spirit and special boiling point industrial spirits | G59: Refined petroleum products
A60: O4692 | B60: RM067 | C60: RME076 | D60: CPA_C19.2 | E60: MF421 | F60: Lubricants | G60: Refined petroleum products
A61: O4693 | B61: RM067 | C61: RME076 | D61: CPA_C19.2 | E61: MF421 | F61: Paraffin waxes | G61: Refined petroleum products
A62: O4694 | B62: RM067 | C62: RME076 | D62: CPA_C19.2 | E62: MF421 | F62: Petroleum coke | G62: Refined petroleum products
A63: O4695 | B63: RM067 | C63: RME076 | D63: CPA_C19.2 | E63: MF421 | F63: Bitumen | G63: Refined petroleum products
A64: O4699 | B64: RM067 | C64: RME076 | D64: CPA_C19.2 | E64: MF421 | F64: Other oil products n.e.c. | G64: Refined petroleum products
A65: P1000 | B65: RM022 | C65: RME023 | D65: CPA_B05.2 | E65: : | F65: Peat and peat products | G65: Lignite
A66: P1100 | B66: : | C66: : | E66: MF411 | F66: Peat
A67: P1200 | B67: : | C67: : | E67: MF411 | F67: Peat products
A68: R5110-5150_W6000RI | B68: : | C68: : | D68: CPA_A02.B | E68: Biomass | F68: Primary solid biofuels
A69: R5111 | B69: : | C69: : | E69: Biomass | F69: Wood pellets
A70: R5160 | B70: : | C70: : | E70: Biomass | F70: Charcoal
A71: R5210B | B71: : | C71: : | D71: CPA_C20.59.59.903 | E71: Biomass | F71: Blended biogasoline
A72: R5210E | B72: : | C72: : | E72: Biomass | F72: Bioethanol
A73: R5210P | B73: : | C73: : | D73: CPA_C20.59.59.903 | E73: Biomass | F73: Pure biogasoline
A74: R5220B | B74: : | C74: : | D74: CPA_C20.59.59.903 | E74: Biomass | F74: Blended biodiesels
A75: R5220P | B75: : | C75: : | D75: CPA_C20.59.59.903 | E75: Biomass | F75: Pure biodiesels
A76: R5230B | B76: : | C76: : | D76: CPA_C20.59.59.903 | E76: Biomass | F76: Blended bio jet kerosene
A77: R5230P | B77: : | C77: : | D77: CPA_C20.59.59.903 | E77: Biomass | F77: Pure bio jet kerosene
A78: R5290 | B78: : | C78: : | D78: CPA_C20.59.59.903 | E78: Biomass | F78: Other liquid biofuels
A79: R5300 | B79: : | C79: : | D79: CPA_D35.2-B | E79: Biomass | F79: Biogases
A80: RA000 | B80: : | C80: : | E80: : | F80: Renewables and biofuels
A81: RA100 | B81: RM124 | C81: RME141 | D81: CPA_D35.1A | E81: Hydro | F81: Hydro | G81: Electricity, transmission and distribution services
A82: RA130 | B82: : | C82: : | E82: : | F82: Pumped hydro power | H82: aggregated position RA100 is used, added 18.03.2024 (pyct)
A83: RA200 | B83: RM126 | C83: RME143 | D83: CPA_D35.3A | E83: Geothermal | F83: Geothermal | G83: Steam and air conditioning supply services
A84: RA300 | B84: RM124 | C84: RME141 | D84: CPA_D35.1B | E84: Wind | F84: Wind | G84: Electricity, transmission and distribution services
A85: RA410 | B85: RM126 | C85: RME143 | D85: CPA_D35.3B | E85: Solar | F85: Solar thermal | G85: Steam and air conditioning supply services
A86: RA420 | B86: RM124 | C86: RME141 | D86: CPA_D35.1C | E86: Solar | F86: Solar photovoltaic | G86: Electricity, transmission and distribution services
A87: RA500 | B87: RM124 | C87: RME141 | D87: CPA_D35.1D | E87: Hydro | F87: Tide, wave, ocean | G87: Electricity, transmission and distribution services
A88: RA600 | B88: RM126 | C88: RME143 | D88: CPA_D35.3C | E88: Other | F88: Ambient heat (heat pumps) | G88: Steam and air conditioning supply services
A89: S2000 | B89: RM024 | C89: RME025 | D89: CPA_B06.10.2 | E89: MF421 | F89: Oil shale and oil sands | G89: Bituminous or oil shale and tar sands
A90: TOTAL | B90: : | C90: : | E90: : | F90: Total
A91: W6100 | B91: : | C91: : | D91: CPA_E38-A | E91: Waste | F91: Industrial waste (non-renewable)
A92: W6100_6220 | B92: : | C92: : | D92: CPA_E38-A | E92: : | F92: Non-renewable waste
A93: W6210 | B93: : | C93: : | D93: CPA_E38-A | E93: Waste | F93: Renewable municipal waste
A94: W6220 | B94: : | C94: : | D94: CPA_E38-A | E94: Waste | F94: Non-renewable municipal waste
A95: X9900 | B95: : | C95: : | E95: : | F95: Other fuels n.e.c. | H95: own allocation, added 18.03.2024 (pyct), to check

Sheet psut_pro
A2: psutp | B2: rmh | C2: remark
A3: EPRD_OUSE | B3: : | C3: not used
A4: N00 | B4: : | C4: not used
A5: N00_P00_R00 | B5: : | C5: not used
A6: N01 | B6: : | C6: not used
A7: N02 | B7: : | C7: not used
A8: N03 | B8: : | C8: not used
A9: N04 | B9: : | C9: not used
A10: N05 | B10: : | C10: not used
A11: N06 | B11: : | C11: not used
A12: N07 | B12: : | C12: not used
A13: P00 | B13: : | C13: not used
... A39: SD_IO | B39: : | C39: Statistical discrepancy, not real product row

Sheet irp_mat
A1: irp | B1: material
A2: All.FeCr | B2: Ferrochrome | C2: =#N/A -> #N/A | D2: =CONCATENATE("TCCC",RIGHT(C2,LEN(C2)-1)) -> #N/A
A3: All.FeMn | B3: Ferromanganese | C3: =#N/A -> #N/A | D3: =CONCATENATE("TCCC",RIGHT(C3,LEN(C3)-1)) -> #N/A
A4: All.FeMo | B4: Ferromolybdenum | C4: =#N/A -> #N/A | D4: =CONCATENATE("TCCC",RIGHT(C4,LEN(C4)-1)) -> #N/A
A5: All.FeNi | B5: Ferronickel | C5: =#N/A -> #N/A | D5: =CONCATENATE("TCCC",RIGHT(C5,LEN(C5)-1)) -> #N/A
A6: All.FeSi | B6: Ferrosilicon | C6: =#N/A -> #N/A | D6: =CONCATENATE("TCCC",RIGHT(C6,LEN(C6)-1)) -> #N/A
A7: All.FeV | B7: Ferrovanadium | C7: =#N/A -> #N/A | D7: =CONCATENATE("TCCC",RIGHT(C7,LEN(C7)-1)) -> #N/A
A8: All.FeW | B8: Ferrotungsten | C8: =#N/A -> #N/A | D8: =CONCATENATE("TCCC",RIGHT(C8,LEN(C8)-1)) -> #N/A
A9: AO.Ag | B9: Silver - associated ore | C9: A.2.2.Ag | D9: =CONCATENATE("TCCC",RIGHT(C9,LEN(C9)-1)) -> TCCC.2.2.Ag
A10: AO.Al | B10: Aluminium - associated ore | C10: =#N/A -> #N/A | D10: =CONCATENATE("TCCC",RIGHT(C10,LEN(C10)-1)) -> #N/A
A11: AO.As | B11: Arsenic - associated ore | C11: =#N/A -> #N/A | D11: =CONCATENATE("TCCC",RIGHT(C11,LEN(C11)-1)) -> #N/A
A12: AO.Au | B12: Gold - associated ore | C12: A.2.2.Au | D12: =CONCATENATE("TCCC",RIGHT(C12,LEN(C12)-1)) -> TCCC.2.2.Au
A13: AO.Be | B13: Beryllium - associated ore | C13: =#N/A -> #N/A | D13: =CONCATENATE("TCCC",RIGHT(C13,LEN(C13)-1)) -> #N/A
A14: AO.Bi | B14: Bismuth - associated ore | C14: A.2.2.nec | D14: =CONCATENATE("TCCC",RIGHT(C14,LEN(C14)-1)) -> TCCC.2.2.nec
A15: AO.Cd | B15: Cadmium - associated ore | C15: =#N/A -> #N/A | D15: =CONCATENATE("TCCC",RIGHT(C15,LEN(C15)-1)) -> #N/A
A16: AO.Co | B16: Cobalt - associated ore | C16: A.2.2.nec | D16: =CONCATENATE("TCCC",RIGHT(C16,LEN(C16)-1)) -> TCCC.2.2.nec
A17: AO.Cr | B17: Chromium - associated ore | C17: A.2.2.Cr | D17: =CONCATENATE("TCCC",RIGHT(C17,LEN(C17)-1)) -> TCCC.2.2.Cr
A18: AO.Cs | B18: Caesium - associated ore | C18: =#N/A -> #N/A | D18: =CONCATENATE("TCCC",RIGHT(C18,LEN(C18)-1)) -> #N/A
A19: AO.Cu | B19: Copper - associated ore | C19: A.2.2.Cu | D19: =CONCATENATE("TCCC",RIGHT(C19,LEN(C19)-1)) -> TCCC.2.2.Cu
A20: AO.Fe | B20: Iron - associated ore | C20: A.2.1.Fe | D20: =CONCATENATE("TCCC",RIGHT(C20,LEN(C20)-1)) -> TCCC.2.1.Fe
A21: AO.Ga | B21: Gallium - associated ore | C21: =#N/A -> #N/A | D21: =CONCATENATE("TCCC",RIGHT(C21,LEN(C21)-1)) -> #N/A
A22: AO.Ge | B22: Germanium - associated ore | C22: =#N/A -> #N/A | D22: =CONCATENATE("TCCC",RIGHT(C22,LEN(C22)-1)) -> #N/A
A23: AO.Hf | B23: Hafnium - associated ore | C23: =#N/A -> #N/A | D23: =CONCATENATE("TCCC",RIGHT(C23,LEN(C23)-1)) -> #N/A
A24: AO.Hg | B24: Mercury - associated ore | C24: A.2.2.nec | D24: =CONCATENATE("TCCC",RIGHT(C24,LEN(C24)-1)) -> TCCC.2.2.nec
A25: AO.In | B25: Indium - associated ore | C25: =#N/A -> #N/A | D25: =CONCATENATE("TCCC",RIGHT(C25,LEN(C25)-1)) -> #N/A
A26: AO.Ir | B26: Iridium - associated ore | C26: A.2.2.Pt | D26: =CONCATENATE("TCCC",RIGHT(C26,LEN(C26)-1)) -> TCCC.2.2.Pt
A27: AO.Li | B27: Lithium - associated ore | C27: A.2.2.nec | D27: =CONCATENATE("TCCC",RIGHT(C27,LEN(C27)-1)) -> TCCC.2.2.nec
A28: AO.Mg | B28: Magnesium - associated ore | C28: =#N/A -> #N/A | D28: =CONCATENATE("TCCC",RIGHT(C28,LEN(C28)-1)) -> #N/A
A29: AO.Mn | B29: Manganese - associated ore | C29: A.2.2.Mn | D29: =CONCATENATE("TCCC",RIGHT(C29,LEN(C29)-1)) -> TCCC.2.2.Mn
A30: AO.Mo | B30: Molybdenum - associated ore | C30: A.2.2.nec | D30: =CONCATENATE("TCCC",RIGHT(C30,LEN(C30)-1)) -> TCCC.2.2.nec
A31: AO.Nb | B31: Niobium - associated ore | C31: A.2.2.nec | D31: =CONCATENATE("TCCC",RIGHT(C31,LEN(C31)-1)) -> TCCC.2.2.nec
A32: AO.Ni | B32: Nickel - associated ore | C32: A.2.2.Ni | D32: =CONCATENATE("TCCC",RIGHT(C32,LEN(C32)-1)) -> TCCC.2.2.Ni
A33: AO.Os | B33: Osmium - associated ore | C33: A.2.2.Pt | D33: =CONCATENATE("TCCC",RIGHT(C33,LEN(C33)-1)) -> TCCC.2.2.Pt
A34: AO.Pb | B34: Lead - associated ore | C34: A.2.2.Pb | D34: =CONCATENATE("TCCC",RIGHT(C34,LEN(C34)-1)) -> TCCC.2.2.Pb
A35: AO.Pd | B35: Palladium - associated ore | C35: A.2.2.Pt | D35: =CONCATENATE("TCCC",RIGHT(C35,LEN(C35)-1)) -> TCCC.2.2.Pt
A36: AO.pgm | B36: PGM - associated ore | C36: A.2.2.Pt | D36: =CONCATENATE("TCCC",RIGHT(C36,LEN(C36)-1)) -> TCCC.2.2.Pt
A37: AO.Pt | B37: Platinum - associated ore | C37: A.2.2.Pt | D37: =CONCATENATE("TCCC",RIGHT(C37,LEN(C37)-1)) -> TCCC.2.2.Pt
A38: AO.Rb | B38: Rubidium - associated ore | C38: =#N/A -> #N/A | D38: =CONCATENATE("TCCC",RIGHT(C38,LEN(C38)-1)) -> #N/A
A39: AO.Re | B39: Rhenium - associated ore | C39: =#N/A -> #N/A | D39: =CONCATENATE("TCCC",RIGHT(C39,LEN(C39)-1)) -> #N/A
A40: AO.rem | B40: REM - associated ore | C40: A.2.2.nec | D40: =CONCATENATE("TCCC",RIGHT(C40,LEN(C40)-1)) -> TCCC.2.2.nec
A41: AO.Rh | B41: Rhodium - associated ore | C41: A.2.2.Pt | D41: =CONCATENATE("TCCC",RIGHT(C41,LEN(C41)-1)) -> TCCC.2.2.Pt
A42: AO.Ru | B42: Ruthenium - associated ore | C42: =#N/A -> #N/A | D42: =CONCATENATE("TCCC",RIGHT(C42,LEN(C42)-1)) -> #N/A
A43: AO.Sb | B43: Antimony - associated ore | C43: A.2.2.nec | D43: =CONCATENATE("TCCC",RIGHT(C43,LEN(C43)-1)) -> TCCC.2.2.nec
A44: AO.Se | B44: Selenium - associated ore | C44: =#N/A -> #N/A | D44: =CONCATENATE("TCCC",RIGHT(C44,LEN(C44)-1)) -> #N/A
A45: AO.Sn | B45: Tin - associated ore | C45: A.2.2.Sn | D45: =CONCATENATE("TCCC",RIGHT(C45,LEN(C45)-1)) -> TCCC.2.2.Sn
A46: AO.Sr | B46: Strontium - associated ore | C46: =#N/A -> #N/A | D46: =CONCATENATE("TCCC",RIGHT(C46,LEN(C46)-1)) -> #N/A
A47: AO.Ta | B47: Tantalum - associated ore | C47: A.2.2.nec | D47: =CONCATENATE("TCCC",RIGHT(C47,LEN(C47)-1)) -> TCCC.2.2.nec
A48: AO.Te | B48: Tellurium - associated ore | C48: A.2.2.nec | D48: =CONCATENATE("TCCC",RIGHT(C48,LEN(C48)-1)) -> TCCC.2.2.nec
A49: AO.Th | B49: Thorium - associated ore | C49: =#N/A -> #N/A | D49: =CONCATENATE("TCCC",RIGHT(C49,LEN(C49)-1)) -> #N/A
A50: AO.Ti | B50: Titanium - associated ore | C50: A.2.2.Ti | D50: =CONCATENATE("TCCC",RIGHT(C50,LEN(C50)-1)) -> TCCC.2.2.Ti
A51: AO.Tl | B51: Thallium - associated ore | C51: =#N/A -> #N/A | D51: =CONCATENATE("TCCC",RIGHT(C51,LEN(C51)-1)) -> #N/A
A52: AO.U | B52: Uranium - associated ore | C52: A.2.2.U | D52: =CONCATENATE("TCCC",RIGHT(C52,LEN(C52)-1)) -> TCCC.2.2.U
A53: AO.V | B53: Vanadium - associated ore | C53: A.2.2.nec | D53: =CONCATENATE("TCCC",RIGHT(C53,LEN(C53)-1)) -> TCCC.2.2.nec
A54: AO.W | B54: Tungsten - associated ore | C54: A.2.2.nec | D54: =CONCATENATE("TCCC",RIGHT(C54,LEN(C54)-1)) -> TCCC.2.2.nec
A55: AO.Zn | B55: Zinc - associated ore | C55: A.2.2.Zn | D55: =CONCATENATE("TCCC",RIGHT(C55,LEN(C55)-1)) -> TCCC.2.2.Zn
A56: AO.Zr | B56: Zirconium - associated ore | C56: =#N/A -> #N/A | D56: =CONCATENATE("TCCC",RIGHT(C56,LEN(C56)-1)) -> #N/A
A57: Con.Ag | B57: Silver concentrate | C57: =#N/A -> #N/A | D57: =CONCATENATE("TCCC",RIGHT(C57,LEN(C57)-1)) -> #N/A
A58: Con.Al | B58: Aluminium concentrate | C58: =#N/A -> #N/A | D58: =CONCATENATE("TCCC",RIGHT(C58,LEN(C58)-1)) -> #N/A
A59: Con.Au | B59: Gold concentrate | C59: =#N/A -> #N/A | D59: =CONCATENATE("TCCC",RIGHT(C59,LEN(C59)-1)) -> #N/A
A60: Con.Be | B60: Beryllium concentrate | C60: =#N/A -> #N/A | D60: =CONCATENATE("TCCC",RIGHT(C60,LEN(C60)-1)) -> #N/A
A61: Con.bulk | B61: Bulk concentrate | C61: =#N/A -> #N/A | D61: =CONCATENATE("TCCC",RIGHT(C61,LEN(C61)-1)) -> #N/A
A62: Con.Co | B62: Cobalt concentrate | C62: =#N/A -> #N/A | D62: =CONCATENATE("TCCC",RIGHT(C62,LEN(C62)-1)) -> #N/A
A63: Con.Cr | B63: Chromium concentrate | C63: =#N/A -> #N/A | D63: =CONCATENATE("TCCC",RIGHT(C63,LEN(C63)-1)) -> #N/A
A64: Con.Cu | B64: Copper concentrate | C64: =#N/A -> #N/A | D64: =CONCATENATE("TCCC",RIGHT(C64,LEN(C64)-1)) -> #N/A
A65: Con.CuS | B65: Copper sulphide concentrate | C65: =#N/A -> #N/A | D65: =CONCATENATE("TCCC",RIGHT(C65,LEN(C65)-1)) -> #N/A
A66: Con.Fe | B66: Iron ore concentrate | C66: =#N/A -> #N/A | D66: =CONCATENATE("TCCC",RIGHT(C66,LEN(C66)-1)) -> #N/A
A67: Con.FeNi | B67: Ferronickel concentrate | C67: =#N/A -> #N/A | D67: =CONCATENATE("TCCC",RIGHT(C67,LEN(C67)-1)) -> #N/A
... A84: Con.Zr | B84: Zirconium concentrate | C84: =#N/A -> #N/A | D84: =CONCATENATE("TCCC",RIGHT(C84,LEN(C84)-1)) -> #N/A
A85: F.ant | B85: Anthracite | C85: A.4.1.2.1 | D85: =CONCATENATE("TCCC",RIGHT(C85,LEN(C85)-1)) -> TCCC.4.1.2.1
A86: F.coal | B86: Coal (unspecified) | C86: =#N/A -> #N/A | D86: =CONCATENATE("TCCC",RIGHT(C86,LEN(C86)-1)) -> #N/A
A87: F.coc | B87: Coking Coal | C87: A.4.1.2.2 | D87: =CONCATENATE("TCCC",RIGHT(C87,LEN(C87)-1)) -> TCCC.4.1.2.2
A88: F.cro | B88: Crude oil | C88: A.4.2.1 | D88: =CONCATENATE("TCCC",RIGHT(C88,LEN(C88)-1)) -> TCCC.4.2.1
A89: F.lig | B89: Lignite | C89: A.4.1.1.1 | D89: =CONCATENATE("TCCC",RIGHT(C89,LEN(C89)-1)) -> TCCC.4.1.1.1
A90: F.nag | B90: Natural gas | C90: A.4.2.2 | D90: =CONCATENATE("TCCC",RIGHT(C90,LEN(C90)-1)) -> TCCC.4.2.2
A91: F.ngl | B91: Natural gas liquids | C91: A.4.2.3 | D91: =CONCATENATE("TCCC",RIGHT(C91,LEN(C91)-1)) -> TCCC.4.2.3
A92: F.obc | B92: Other bituminous coal | C92: A.4.1.2.3 | D92: =CONCATENATE("TCCC",RIGHT(C92,LEN(C92)-1)) -> TCCC.4.1.2.3
A93: F.ois | B93: Oil shale and oil sands | C93: A.4.3 | D93: =CONCATENATE("TCCC",RIGHT(C93,LEN(C93)-1)) -> TCCC.4.3
A94: F.oth | B94: Other hydrocarbons | C94: =#N/A -> #N/A | D94: =CONCATENATE("TCCC",RIGHT(C94,LEN(C94)-1)) -> #N/A
A95: F.pea | B95: Peat for energy use | C95: A.4.1.3 | D95: =CONCATENATE("TCCC",RIGHT(C95,LEN(C95)-1)) -> TCCC.4.1.3
A96: F.sbc | B96: Sub-bituminous coal | C96: A.4.1.1.2 | D96: =CONCATENATE("TCCC",RIGHT(C96,LEN(C96)-1)) -> TCCC.4.1.1.2
A97: Ff.ois | B97: Petroleum from oil sands | C97: =#N/A -> #N/A | D97: =CONCATENATE("TCCC",RIGHT(C97,LEN(C97)-1)) -> #N/A
A98: M.abr | B98: Abrasives, natural (puzzolan, pumice, volcanic cinder etc.) | C98: A.3.4.3 | D98: =CONCATENATE("TCCC",RIGHT(C98,LEN(C98)-1)) -> TCCC.3.4.3
A99: M.amb | B99: Amber | C99: =#N/A -> #N/A | D99: =CONCATENATE("TCCC",RIGHT(C99,LEN(C99)-1)) -> #N/A
A100: M.asb | B100: Asbestos | C100: A.3.4.3 | D100: =CONCATENATE("TCCC",RIGHT(C100,LEN(C100)-1)) -> TCCC.3.4.3
A101: M.asp | B101: Asphalt | C101: A.3.9 | D101: =CONCATENATE("TCCC",RIGHT(C101,LEN(C101)-1)) -> TCCC.3.9
A102: M.bac | B102: Ball clay | C102: A.3.7.2 | D102: =CONCATENATE("TCCC",RIGHT(C102,LEN(C102)-1)) -> TCCC.3.7.2
A103: M.bar | B103: Barite | C103: A.3.4.2 | D103: =CONCATENATE("TCCC",RIGHT(C103,LEN(C103)-1)) -> TCCC.3.4.2
A104: M.ben | B104: Bentonite, sepiolite and attapulgite | C104: A.3.7.2 | D104: =CONCATENATE("TCCC",RIGHT(C104,LEN(C104)-1)) -> TCCC.3.7.2
A105: M.bor | B105: Borate minerals | C105: A.3.4.2 | D105: =CONCATENATE("TCCC",RIGHT(C105,LEN(C105)-1)) -> TCCC.3.4.2
A106: M.bro | B106: Bromine | C106: A.3.4.3 | D106: =CONCATENATE("TCCC",RIGHT(C106,LEN(C106)-1)) -> TCCC.3.4.3
A107: M.brs | B107: Brine salt | C107: A.3.5 | D107: =CONCATENATE("TCCC",RIGHT(C107,LEN(C107)-1)) -> TCCC.3.5
A108: M.cal | B108: Calcite | C108: A.3.2.3 | D108: =CONCATENATE("TCCC",RIGHT(C108,LEN(C108)-1)) -> TCCC.3.2.3
A109: M.cha | B109: Chalk | C109: A.3.2.1 | D109: =CONCATENATE("TCCC",RIGHT(C109,LEN(C109)-1)) -> TCCC.3.2.1
A110: M.chf | B110: Chert and flint | C110: A.3.9 | D110: =CONCATENATE("TCCC",RIGHT(C110,LEN(C110)-1)) -> TCCC.3.9
A111: M.coc | B111: Common clay, clay for bricks etc. | C111: A.3.7.1 | D111: =CONCATENATE("TCCC",RIGHT(C111,LEN(C111)-1)) -> TCCC.3.7.1
A112: M.con | B112: Construction Minerals nec | C112: =#N/A -> #N/A | D112: =CONCATENATE("TCCC",RIGHT(C112,LEN(C112)-1)) -> #N/A
A113: M.crs | B113: Crushed stone | C113: A.3.8.2 | D113: =CONCATENATE("TCCC",RIGHT(C113,LEN(C113)-1)) -> TCCC.3.8.2
A114: M.dia | B114: Diatomite | C114: A.3.4.3 | D114: =CONCATENATE("TCCC",RIGHT(C114,LEN(C114)-1)) -> TCCC.3.4.3
A115: M.dim | B115: Dimension stone n.e.c. | C115: A.3.1 | D115: =CONCATENATE("TCCC",RIGHT(C115,LEN(C115)-1)) -> TCCC.3.1
A116: M.dol | B116: Dolomite | C116: A.3.2.2 | D116: =CONCATENATE("TCCC",RIGHT(C116,LEN(C116)-1)) -> TCCC.3.2.2
...

Sheet irp_intermediate
A1: irp_ore | B1: ore_label | C1: ore | D1: associated_ore | E1: ccc | F1: material
A2: Me.Fe | B2: Iron | C2: O.Fe | D2: AO.Fe | E2: TCCC.A.2.1.Fe | F2: Fe | J2: A.2.1.Fe
A3: Me.Ag | B3: Silver | C3: O.Ag | D3: AO.Ag | E3: TCCC.A.2.2.Ag | F3: Ag | J3: A.2.2.Ag
A4: Me.Au | B4: Gold | C4: O.Au | D4: AO.Au | E4: TCCC.A.2.2.Au | F4: Au | J4: A.2.2.Al
A5: Me.Cr | B5: Chromium | C5: O.Cr | D5: AO.Cr | E5: TCCC.A.2.2.Cr | F5: Cr | J5: A.2.2.Au
A6: Me.Cu | B6: Copper | C6: O.Cu | D6: AO.Cu | E6: TCCC.A.2.2.Cu | F6: Cu | J6: A.2.2.Cr
A7: Me.Hg | B7: Mercury | C7: O.Hg | D7: AO.Hg | E7: TCCC.A.2.2.nec | F7: Hg | J7: A.2.2.Cu
A8: Me.Ir | B8: Iridium | C8: O.Ir | D8: AO.Ir | E8: TCCC.A.2.2.nec | F8: Ir | J8: A.2.2.Mn
A9: Me.K2O | B9: Potassium oxide | C9: O.K20 | D9: AO.K20 | E9: TCCC.A.2.2.nec | F9: K20 | J9: A.2.2.nec
A10: Me.Li2O | B10: Lithium oxide | C10: O.Li2O | D10: AO.Li2O | E10: TCCC.A.2.2.nec | F10: Li2O | J10: A.2.2.Ni
A11: Me.Mn | B11: Manganese | C11: O.Mn | D11: AO.Mn | E11: TCCC.A.2.2.Mn | F11: Mn | J11: A.2.2.Pb
A12: Me.Mo | B12: Molybdenum | C12: O.Mo | D12: AO.Mo | E12: TCCC.A.2.2.nec | F12: Mo | J12: A.2.2.Pt
A13: Me.Nb | B13: Niobium | C13: O.Nb | D13: AO.Nb | E13: TCCC.A.2.2.nec | F13: Nb | J13: A.2.2.Sn
... A16: Me.Ni | B16: Nickel | C16: O.Ni | D16: AO.Ni | E16: TCCC.A.2.2.Ni | F16: Ni | J16: A.2.2.Zn
A17: Me.Os | B17: Osmium | C17: O.Os | D17: AO.Os | E17: TCCC.A.2.2.nec | F17: Os
A18: Me.Pb | B18: Lead | C18: O.Pb | D18: AO.Pb | E18: TCCC.A.2.2.Pb | F18: Pb
A19: Me.Pd | B19: Palladium | C19: O.Pd | D19: AO.Pd | E19: TCCC.A.2.2.Pt | F19: Pd
A20: Me.Pt | B20: Platinum | C20: O.Pt | D20: AO.Pt | E20: TCCC.A.2.2.Pt | F20: Pt
A21: Me.reo | B21: Rare-earth oxides | C21: O.reo | D21: AO.reo | E21: TCCC.A.2.2.nec | F21: reo
A22: Me.Rh | B22: Rhodium | C22: O.Rh | D22: AO.Rh | E22: TCCC.A.2.2.Rh | F22: Rh
A23: Me.Ru | B23: Ruthenium | C23: O.Ru | D23: AO.Ru | E23: TCCC.A.2.2.Ru | F23: Ru
A24: Me.Sb | B24: Antimony | C24: O.Sb | D24: AO.Sb | E24: TCCC.A.2.2.Sb | F24: Sb
A25: Me.Sn | B25: Tin | C25: O.Sn | D25: AO.Sn | E25: TCCC.A.2.2.Sn | F25: Sn
A26: Me.Ta | B26: Tantalum | C26: O.Ta | D26: AO.Ta | E26: TCCC.A.2.2.Ta | F26: Ta
A27: Me.Te | B27: Tellurium | C27: O.Te | D27: AO.Te | E27: TCCC.A.2.2.Te | F27: Te
A28: Me.Ti | B28: Titanium | C28: O.Ti | D28: AO.Ti | E28: TCCC.A.2.2.Ti | F28: Ti
... A32: Me.Zn | B32: Zinc | C32: O.Zn | D32: AO.Zn | E32: TCCC.A.2.2.Zn | F32: Zn
A34: A.2.1.Fe | B34: O.Fe
A35: A.2.1.Fe | B35: AO.Fe
A36: A.2.2.Ag | B36: AO.Ag
A37: A.2.2.Al | B37: O.Al
A38: A.2.2.Au | B38: AO.Au
A39: A.2.2.Cr | B39: AO.Cr
A40: A.2.2.Cr | B40: O.Cr
A41: A.2.2.Cu | B41: AO.Cu
A42: A.2.2.Mn | B42: O.Mn
A43: A.2.2.Mn | B43: AO.Mn
A44: A.2.2.nec | B44: AO.Bi
A45: A.2.2.nec | B45: AO.Co
... A162: A.4.3 | B162: F.ois

Sheet cpa
A2: cpa | B2: rm | C2: cpa_agg | D2: cpa_label
A3: CPA_A01 | B3: CPA_A01 | C3: CPA_A | D3: Products of agriculture, hunting and related services
A4: CPA_A02 | B4: RM019 | C4: CPA_A | D4: Products of forestry, logging and related services
A5: CPA_A03 | B5: RM020 | C5: CPA_A | D5: Fish and other fishing products; aquaculture products; support services to fishing
A6: CPA_B | B6: CPA_B | C6: CPA_B | D6: Mining and quarrying
A7: CPA_B05 | B7: CPA_B05 | C7: CPA_B
A8: CPA_B06 | B8: CPA_B06 | C8: CPA_B
A9: CPA_B07-09 | B9: CPA_B07-09 | C9: CPA_B
A10: CPA_C10-12 | B10: CPA_C10-12 | C10: CPA_C | D10: Food, beverages and tobacco products
A11: CPA_C13-15 | B11: CPA_C13-15 | C11: CPA_C | D11: Textiles, wearing apparel, leather and related products
A12: CPA_C16 | B12: RM062 | C12: CPA_C | D12: Wood and of products of wood and cork, except furniture; articles of straw and plaiting materials
A13: CPA_C17 | B13: CPA_C17 | C13: CPA_C | D13: Paper and paper products
A14: CPA_C18 | B14: RM065 | C14: CPA_C | D14: Printing and recording services
A15: CPA_C19 | B15: CPA_C19 | C15: CPA_C | D15: Coke and refined petroleum products
A16: CPA_C20 | B16: CPA_C20 | C16: CPA_C | D16: Chemicals and chemical products
A17: CPA_C21 | B17: RM076 | C17: CPA_C | D17: Basic pharmaceutical products and pharmaceutical preparations
A18: CPA_C22 | B18: CPA_C22 | C18: CPA_C | D18: Rubber and plastic products
A19: CPA_C23 | B19: CPA_C23 | C19: CPA_C | D19: Other non-metallic mineral products
A20: CPA_C23.1 | B20: CPA_C23.1 | C20: CPA_C
A21: CPA_C23.2-23.9 | B21: CPA_C23.2-23.9 | C21: CPA_C
A22: CPA_C24.1-24.3 | B22: CPA_C24.1-24.3 | C22: CPA_C
A23: CPA_C24.4 | B23: CPA_C24.4 | C23: CPA_C
A24: CPA_C24.5 | B24: CPA_C24.5 | C24: CPA_C
A25: CPA_C24 | B25: CPA_C24 | C25: CPA_C | D25: Basic metals
A26: CPA_C25 | B26: CPA_C25 | C26: CPA_C | D26: Fabricated metal products, except machinery and equipment
A27: CPA_C26 | B27: RM108 | C27: CPA_C | D27: Computer, electronic and optical products
A28: CPA_C27 | B28: RM109 | C28: CPA_C | D28: Electrical equipment
A29: CPA_C28 | B29: RM110 | C29: CPA_C | D29: Machinery and equipment n.e.c.
A30: CPA_C29 | B30: RM111 | C30: CPA_C | D30: Motor vehicles, trailers and semi-trailers
A31: CPA_C30 | B31: CPA_C30 | C31: CPA_C | D31: Other transport equipment
A32: CPA_C31_32 | B32: CPA_C31_32 | C32: CPA_C | D32: Furniture and other manufactured goods
A33: CPA_C33 | B33: RM123 | C33: CPA_C | D33: Repair and installation services of machinery and equipment
A34: CPA_D35 | B34: CPA_D35 | C34: CPA_D35 | D34: Electricity, gas, steam and air conditioning
A35: CPA_D35.1_35.3 | B35: CPA_D35.1_35.3 | C35: CPA_D35
A36: CPA_D35.2 | B36: CPA_D35.2 | C36: CPA_D35
A37: CPA_E36 | B37: RM127 | C37: CPA_E | D37: Natural water; water treatment and supply services
A38: CPA_E37-39 | B38: RM128 | C38: CPA_E | D38: Sewerage services; sewage sludge; waste collection, treatment and disposal services; materials recovery services; remediation services and other waste management services
A39: CPA_F | B39: RM129 | C39: CPA_F | D39: Constructions and construction works
A40: CPA_G45 | B40: RM130 | C40: CPA_G | D40: Wholesale and retail trade and repair services of motor vehicles and motorcycles
A41: CPA_G46 | B41: RM131 | C41: CPA_G | D41: Wholesale trade services, except of motor vehicles and motorcycles
A42: CPA_G47 | B42: RM132 | C42: CPA_G | D42: Retail trade services, except of motor vehicles and motorcycles
A43: CPA_H49 | B43: RM133 | C43: CPA_H | D43: Land transport services and transport services via pipelines
A44: CPA_H50 | B44: RM134 | C44: CPA_H | D44: Water transport services
A45: CPA_H51 | B45: RM135 | C45: CPA_H | D45: Air transport services
A46: CPA_H52 | B46: RM136 | C46: CPA_H | D46: Warehousing and support services for transportation
A47: CPA_H53 | B47: RM137 | C47: CPA_H | D47: Postal and courier services
A48: CPA_I | B48: RM138 | C48: CPA_I | D48: Accommodation and food services
... A73: CPA_S95 | B73: RM163 | C73: CPA_S | D73: Repair services of computers and personal and household goods
A74: CPA_S96 | B74: RM164 | C74: CPA_S
A75: CPA_S96_U | B75: RM164_166 | C75: CPA_S | D75: Other personal services
A76: CPA_T | B76: RM165 | C76: CPA_T | D76: Services of households as employers; undifferentiated goods and services produced by households for own use
A77: CPA_U | B77: RM166 | C77: CPA_U
A78: TOTAL | B78: TOTAL | C78: TOTAL

Sheet iea_pro
A2: iea_pro | B2: iea_label
A3: HARDCOAL | B3: Hard coal (if no detail)
A4: BROWN | B4: Brown coal (if no detail)
A5: ANTCOAL | B5: Anthracite
A6: COKCOAL | B6: Coking coal
A7: BITCOAL | B7: Other bituminous coal
A8: SUBCOAL | B8: Sub-bituminous coal
A9: LIGNITE | B9: Lignite
A10: PATFUEL | B10: Patent fuel
A11: OVENCOKE | B11: Coke oven coke
A12: GASCOKE | B12: Gas coke
A13: COALTAR | B13: Coal tar
... A70: MRENEW | B70: Memo: Renewables

Sheet psut_ind_bridge
A1: Add additional column for mapping to rmh codes (see sheet iea)
A2: flow | B2: psut_ind | C2: ind | D2: rmh | E2: method | F2: remark
A3: USE | B3: A01 | C3: 01, 02 | D3: RM001-018_019.1-019.2 | E3: direct | F3: crop and animal production
A4: USE | B4: A02 | C4: 01, 02 | D4: RM001-018_019.1-019.2 | E4: direct | F4: forestry
A5: USE | B5: A03 | C5: 03 | D5: RM020 | E5: direct | F5: fishing
A6: USE | B6: B | C6: 05 | D6: RM021-022 | E6: eb_share | F6: mining split
A7: USE | B7: B | C7: 06 | D7: RM023-025 | E7: eb_share | F7: mining split
A8: USE | B8: B | C8: 07, 08, 09.9 | D8: RM026-048 | E8: eb_share | F8: mining split
A9: USE | B9: C10-C12 | C9: 10, 11, 12 | D9: RM049-058 | E9: direct | F9: food, beverages, tobacco
A10: USE | B10: C13-C15 | C10: 13, 14, 15 | D10: RM059-061 | E10: direct | F10: textiles, leather
A11: USE | B11: C16 | C11: 16 | D11: RM062 | E11: direct | F11: wood
A12: USE | B12: C17 | C12: 17, 18 | D12: RM063-065 | E12: direct | F12: paper
A13: USE | B13: C18 | C13: 17, 18 | D13: RM063-065 | E13: direct | F13: printing
... A185: SUPPLY | B185: ENV | C185: : | D185: : | E185: drop | F185: supply detail/aggregate row; drop

Sheet Tabelle1
A3: nrgp | B3: rme | C3: rm | D3: cpa28 | E3: mfa | F3: nrgp_label | G3: rme_label | M3: nrgp | Q3: Hard coal (if no detail)
A4: BA100 | B4: RME141 | C4: RM124 | E4: Other | F4: Batteries | G4: Electricity, transmission and distribution services | H4: added 18.03.2024 (pyct) | M4: TOTAL | Q4: Brown coal (if no detail)
A5: BIOE | B5: : | C5: : | E5: : | F5: Bioenergy | M5: BKB | Q5: Anthracite
A6: C0000X0350-0370 | B6: : | C6: : | E6: : | F6: Solid fossil fuels | M6: ADDITIVES | Q6: Coking coal
A7: C0100 | B7: : | C7: : | E7: : | F7: Hard coal | H7: aggregate | M7: ANTHRACITE | N7: RM021 | Q7: Other bituminous coal
A8: C0110 | B8: RME022 | C8: RM021 | D8: CPA_B05.1 | E8: MF412 | F8: Anthracite | G8: Hard coal | M8: AVIATION_GASOLINE | Q8: Sub-bituminous coal
A9: C0121 | B9: RME022 | C9: RM021 | E9: MF412 | F9: Coking coal | G9: Hard coal | M9: BIODIESEL | Q9: Lignite
A10: C0129 | B10: RME022 | C10: RM021 | E10: MF412 | F10: Other bituminous coal | G10: Hard coal | M10: BIOFUEL_NONSPEC | Q10: Patent fuel
A11: C0200 | B11: : | C11: : | E11: : | F11: Brown coal | H11: aggregate | M11: BIOGASES | Q11: Coke oven coke
A12: C0210 | B12: RME023 | C12: RM022 | D12: CPA_B05.2 | E12: MF411 | F12: Sub-bituminous coal | G12: Lignite | M12: BIOGASOLINE | Q12: Gas coke
A13: C0220 | B13: RME023 | C13: RM022 | E13: MF411 | F13: Lignite | G13: Lignite | M13: BITUMEN | Q13: Coal tar
A14: C0311 | B14: RME075 | C14: RM066 | E14: MF412 | F14: Coke oven coke | G14: Coke oven products | M14: BLAST_FURNACE_GAS | Q14: BKB
A15: C0312 | B15: RME075 | C15: RM066 | E15: MF412 | F15: Gas coke | G15: Coke oven products | M15: BROWNCOAL_ND | Q15: Gas works gas
A16: C0320 | B16: RME076 | C16: RM067 | E16: MF412 | F16: Patent fuel | G16: Refined petroleum products | M16: CHARCOAL | Q16: Coke oven gas
A17: C0330 | B17: RME076 | C17: RM067 | E17: MF411 | F17: Brown coal briquettes | G17: Refined petroleum products | M17: COAL_TAR | Q17: Blast furnace gas
A18: C0340 | B18: RME075 | C18: RM066 | E18: MF412 | F18: Coal tar | G18: Coke oven products | M18: COKE_OVEN_COKE_OTH | Q18: Other recovered gases
A19: C0350 | B19: RME075 | C19: RM066 | E19: MF422 | F19: Coke oven gas | G19: Coke oven products | M19: COKE_OVEN_GAS | Q19: Peat
A20: C0350-0370 | B20: : | C20: : | E20: : | F20: Manufactured gases | M20: COKING_COAL | Q20: Peat products
A21: C0360 | B21: : | C21: : | E21: MF422 | F21: Gas works gas | M21: CRUDE_OIL | Q21: Oil shale and oil sands
A22: C0371 | B22: : | C22: : | E22: MF422 | F22: Blast furnace gas | M22: ELECTRICITY | Q22: Natural gas
A23: C0379 | B23: : | C23: : | E23: MF422 | F23: Other recovered gases | M23: ETHANE | Q23: Crude/NGL/feedstocks (if no detail)
A24: E7000 | B24: RME141 | C24: RM124 | E24: Waste | F24: Electricity | G24: Electricity, transmission and distribution services | M24: FUEL_OIL_RESIDUAL | Q24: Crude oil
A25: FE | B25: : | C25: : | E25: : | F25: Fossil energy | M25: GASOLINE_JET | Q25: Natural gas liquids
A26: G3000 | B26: RME026 | C26: RM025 | E26: MF422 | F26: Natural gas | G26: Natural gas, liquefied or in gaseous state | M26: GASWORKS_GAS | Q26: Refinery feedstocks
A27: G3200 | B27: : | C27: : | E27: : | F27: Liquified natural gas | H27: sub-aggregate | M27: GAS_COKE | Q27: Additives/blending components
A28: H8000 | B28: RME143 | C28: RM126 | E28: Waste | F28: Heat | G28: Steam and air conditioning supply services | M28: GAS_DIESEL_OIL_NONBIO | Q28: Other hydrocarbons
A29: N900H | B29: RME113 | C29: RM098 | E29: MF228 | F29: Nuclear heat | G29: Processed nuclear fuel | M29: GEOTHERMAL | Q29: Refinery gas
A30: O4000 | B30: : | C30: : | E30: : | F30: Oil and petroleum products | M30: HARDCOAL_ND | Q30: Ethane
A31: O4000XBIO | B31: : | C31: : | E31: : | F31: Oil and petroleum products (excluding biofuel portion) | M31: HEAT | Q31: Liquefied petroleum gases (LPG)
A32: O4100_TOT | B32: RME024 | C32: RM023 | E32: MF421 | F32: Crude oil | G32: Petroleum oils and oils obtained from bituminous minerals, crude | M32: HEAT_COMBUSTIBLES_NS | Q32: Motor gasoline excl. biofuels
A33: O4100_TOT_4200-4500 | B33: : | C33: : | E33: : | F33: Crude oil, NGL, refinery feedstocks, additives and oxygenates and other hydrocarbons | M33: HYDRO | Q33: Aviation gasoline
A34: O4100_TOT_4200-4500XBIO | B34: : | C34: : | E34: : | F34: Crude oil, NGL, refinery feedstocks, additives and oxygenates and other hydrocarbons (excluding biofuel portion) | M34: HYDROCARBONS_OTHER | Q34: Gasoline type jet fuel
A35: O4200 | B35: RME024 | C35: RM023 | E35: MF421 | F35: Natural gas liquids | G35: Petroleum oils and oils obtained from bituminous minerals, crude | M35: KEROSENE_JET_BIO | Q35: Kerosene type jet fuel excl. biofuels
A36: O4300 | B36: RME076 | C36: RM067 | E36: MF421 | F36: Refinery feedstocks | G36: Refined petroleum products | M36: KEROSENE_JET_NONBIO | Q36: Other kerosene
A37: O4400 | B37: : | C37: : | E37: : | F37: Additives and oxygenates | M37: KEROSENE_OTHER | Q37: Gas/diesel oil excl. biofuels
A38: O4400X4410 | B38: RME076 | C38: RM067 | E38: MF421 | F38: Additives and oxygenates (excluding biofuel portion) | G38: Refined petroleum products | M38: LIGNITE | Q38: Fuel oil
A39: O4500 | B39: RME076 | C39: RM067 | E39: MF421 | F39: Other hydrocarbons | G39: Refined petroleum products | M39: LIQBIOFUEL_OTHER | Q39: Naphtha
A40: O4600 | B40: : | C40: : | E40: : | F40: Oil products | M40: LPG | Q40: White spirit & SBP
A41: O4600XBIO | B41: : | C41: : | E41: ; | F41: Oil products (excluding biofuel portion) | M41: LUBRICANTS | Q41: Lubricants
A42: O4610 | B42: RME076 | C42: RM067 | E42: MF421 | F42: Refinery gas | G42: Refined petroleum products | M42: MANUFACTURED_GAS_OUTPUT | Q42: Bitumen
A43: O4620 | B43: RME076 | C43: RM067 | E43: MF421 | F43: Ethane | G43: Refined petroleum products | M43: MOTOR_GASOLINE_NONBIO | Q43: Paraffin waxes
A44: O4630 | B44: RME076 | C44: RM067 | E44: MF421 | F44: Liquefied petroleum gases | G44: Refined petroleum products | M44: NAPHTHA | Q44: Petroleum coke
A45: O4640 | B45: RME076 | C45: RM067 | E45: MF421 | F45: Naphtha | G45: Refined petroleum products | M45: NATURAL_GAS | N45: RM025 | Q45: Other oil products
A46: O4651 | B46: RME076 | C46: RM067 | E46: MF421 | F46: Aviation gasoline | G46: Refined petroleum products | M46: NGL | N46: RM023 | Q46: Industrial waste
A47: O4652 | B47: : | C47: : | E47: : | F47: Motor gasoline | M47: NUCLEAR | Q47: Municipal waste (renewable)
A48: O4652XR5210B | B48: RME076 | C48: RM067 | E48: MF421 | F48: Motor gasoline (excluding biofuel portion) | G48: Refined petroleum products | M48: OIL_PRIM_PRODUCTS_ND | Q48: Municipal waste (non-renewable)
A49: O4653 | B49: RME076 | C49: RM067 | E49: MF421 | F49: Gasoline-type jet fuel | G49: Refined petroleum products | M49: OIL_SHALE | Q49: Primary solid biofuels
A50: O4661 | B50: : | C50: : | E50: : | F50: Kerosene-type jet fuel | M50: OTH_BITCOAL | Q50: Biogases
A51: O4661XR5230B | B51: RME076 | C51: RM067 | E51: MF421 | F51: Kerosene-type jet fuel (excluding biofuel portion) | G51: Refined petroleum products | M51: OTH_ENSOURC | Q51: Biogasoline
A52: O4669 | B52: RME076 | C52: RM067 | E52: MF421 | F52: Other kerosene | G52: Refined petroleum products | M52: OTH_RECOVGASES | Q52: Biodiesels
A53: O4671 | B53: : | C53: : | E53: : | F53: Gas oil and diesel oil | M53: OTH_SEC_OIL_PRODS_ND | Q53: Bio jet kerosene
A54: O46711 | B54: : | C54: : | E54: : | F54: Road diesel | M54: PARAFFIN_WAXES | Q54: Other liquid biofuels
A55: O46712 | B55: : | C55: : | E55: : | F55: Heating and other gasoil | M55: PATENT_FUEL | Q55: Non-specified primary biofuels and waste
A56: O4671XR5220B | B56: RME076 | C56: RM067 | E56: MF421 | F56: Gas oil and diesel oil (excluding biofuel portion) | G56: Refined petroleum products | M56: PEAT | Q56: Charcoal
A57: O4680 | B57: RME076 | C57: RM067 | E57: MF421 | F57: Fuel oil | G57: Refined petroleum products | M57: PEAT_PRODUCTS | Q57: Elec/heat output from non-specified manufactured gases
A58: O4681 | B58: : | C58: : | E58: : | F58: Fuel oil (low sulphur <1%) | M58: PETROLEUM_COKE | Q58: Heat output from non-specified combustible fuels
A59: O4682 | B59: : | C59: : | E59: : | F59: Fuel oil (high sulphur >=1%) | M59: PRIMARY_SOLID_BIOFUEL | Q59: Nuclear
A60: O4691 | B60: RME076 | C60: RM067 | E60: MF421 | F60: White spirit and special boiling point industrial spirits | G60: Refined petroleum products | M60: REFINERY_FEEDSTOCKS | Q60: Hydro
A61: O4692 | B61: RME076 | C61: RM067 | E61: MF421 | F61: Lubricants | G61: Refined petroleum products | M61: REFINERY_GAS | Q61: Geothermal
A62: O4693 | B62: RME076 | C62: RM067 | E62: MF421 | F62: Paraffin waxes | G62: Refined petroleum products | M62: RENEWABLES_TOTAL | Q62: Solar photovoltaics
A63: O4694 | B63: RME076 | C63: RM067 | E63: MF421 | F63: Petroleum coke | G63: Refined petroleum products | M63: SOLAR_PV | Q63: Solar thermal
A64: O4695 | B64: RME076 | C64: RM067 | E64: MF421 | F64: Bitumen | G64: Refined petroleum products | M64: SOLAR_THERMAL | Q64: Tide, wave and ocean
A65: O4699 | B65: RME076 | C65: RM067 | E65: MF421 | F65: Other oil products n.e.c. | G65: Refined petroleum products | M65: SUB_BITCOAL | Q65: Wind
A66: P1000 | B66: RME023 | C66: RM022 | E66: : | F66: Peat and peat products | G66: Lignite | M66: TIDAL_WAVE_OCEAN | Q66: Other sources
A67: P1100 | B67: : | C67: : | E67: MF411 | F67: Peat | M67: WASTE_INDUSTRIAL_NONREN | Q67: Electricity
A68: P1200 | B68: : | C68: : | E68: MF411 | F68: Peat products | M68: WASTE_MUNICIPAL_NONREN | Q68: Heat
A69: R5110-5150_W6000RI | B69: : | C69: : | E69: Biomass | F69: Primary solid biofuels | M69: WASTE_MUNICIPAL_REN | Q69: Total
A70: R5111 | B70: : | C70: : | E70: Biomass | F70: Wood pellets | M70: WHITE_SPIRIT | Q70: Memo: Renewables
A71: R5160 | B71: : | C71: : | E71: Biomass | F71: Charcoal | M71: WIND | Q71: Fuel for conventional drive
A72: R5210B | B72: : | C72: : | E72: Biomass | F72: Blended biogasoline | Q72: Fuel for electric drive
A73: R5210E | B73: : | C73: : | E73: Biomass | F73: Bioethanol
A74: R5210P | B74: : | C74: : | E74: Biomass | F74: Pure biogasoline
A75: R5220B | B75: : | C75: : | E75: Biomass | F75: Blended biodiesels
A76: R5220P | B76: : | C76: : | E76: Biomass | F76: Pure biodiesels
A77: R5230B | B77: : | C77: : | E77: Biomass | F77: Blended bio jet kerosene
A78: R5230P | B78: : | C78: : | E78: Biomass | F78: Pure bio jet kerosene
A79: R5290 | B79: : | C79: : | E79: Biomass | F79: Other liquid biofuels
A80: R5300 | B80: : | C80: : | E80: Biomass | F80: Biogases
A81: RA000 | B81: : | C81: : | E81: : | F81: Renewables and biofuels
A82: RA100 | B82: RME141 | C82: RM124 | E82: Hydro | F82: Hydro | G82: Electricity, transmission and distribution services
A83: RA130 | B83: : | C83: : | E83: : | F83: Pumped hydro power | H83: aggregated position RA100 is used, added 18.03.2024 (pyct)
A84: RA200 | B84: RME143 | C84: RM126 | E84: Geothermal | F84: Geothermal | G84: Steam and air conditioning supply services
A85: RA300 | B85: RME141 | C85: RM124 | E85: Wind | F85: Wind | G85: Electricity, transmission and distribution services
A86: RA410 | B86: RME143 | C86: RM126 | E86: Solar | F86: Solar thermal | G86: Steam and air conditioning supply services
A87: RA420 | B87: RME141 | C87: RM124 | E87: Solar | F87: Solar photovoltaic | G87: Electricity, transmission and distribution services
A88: RA500 | B88: RME141 | C88: RM124 | E88: Hydro | F88: Tide, wave, ocean | G88: Electricity, transmission and distribution services
A89: RA600 | B89: RME143 | C89: RM126 | E89: Other | F89: Ambient heat (heat pumps) | G89: Steam and air conditioning supply services
A90: S2000 | B90: RME025 | C90: RM024 | D90: CPA_B06.10.2 | E90: MF421 | F90: Oil shale and oil sands | G90: Bituminous or oil shale and tar sands
A91: TOTAL | B91: : | C91: : | E91: : | F91: Total
A92: W6100 | B92: : | C92: : | E92: Waste | F92: Industrial waste (non-renewable)
A93: W6100_6220 | B93: : | C93: : | E93: : | F93: Non-renewable waste
A94: W6210 | B94: : | C94: : | E94: Waste | F94: Renewable municipal waste
A95: W6220 | B95: : | C95: : | E95: Waste | F95: Non-renewable municipal waste
A96: X9900 | B96: : | C96: : | E96: : | F96: Other fuels n.e.c. | H96: own allocation, added 18.03.2024 (pyct), to check

Sheet rme_nrg
A2: rme_nrg | B2: cpa_label | C2: cpa
A3: RME001-020 | B3: Agriculture and forestry | C3: A01_02
A4: RME021 | B4: Fish and other fishing products; aquaculture products; support services to fishing | C4: CPA_A03
A5: RME022-023 | B5: Coal mining | C5: B05
A6: RME024-026 | B6: Oil and gas extrtaction | C6: B06
A7: RME027-056 | B7: Mining (excluding energy producing industries) and quarrying | C7: B07_08_09.9
A8: RME057-067 | B8: Food products, beverages and tobacco products | C8: CPA_C10-12
A9: RME068-070 | B9: Textiles, wearing apparel and leather products | C9: CPA_C13-15
A10: RME071 | B10: Wood and of products of wood and cork, except furniture; articles of straw and plaiting | C10: CPA_C16
A11: RME072-074 | B11: Paper, pulp and printing | C11: C17_18
A12: RME075 | B12: Coke oven products | C12: C19.1
A13: RME076 | B13: Refined petroleum products | C13: C19.2
... A31: RME173 | B31: Public administration and defence services; compulsory social security services (military fuels | C31: CPA_O84
A32: xRME076_141
A33: xRME141_143
A34: OUT
A35: -OUT
A36: HFCE
A37: -CINV
A38: EXP
A39: IMP

Sheet mfa_bunk
A2: mfa_bunk | B2: ind | C2: pro | D2: bunk_label
A3: MF423 | B3: : | C3: : | D3: Fuels bunkered (Imports: by resident units abroad); (Exports: by non-resident units domestically)
A4: MF4231 | B4: RME150 | C4: RME076 | D4: Fuel for land transport
A5: MF4232 | B5: RME151 | C5: RME076 | D5: Fuel for water transport
A6: MF4233 | B6: RME152 | C6: RME076 | D6: Fuel for air transport

Sheet rme
A2: rme | B2: cpa | C2: rm | D2: cpa_rme | E2: diot | F2: cpa_sut | G2: cpa_agri | H2: rme_nrg | I2: rme_sbs | J2: rme_label | K2: rm_label | L2: rme_label_long
A3: RME001 | B3: CPA_A01 | C3: =VLOOKUP(A3,new!$A$2:$B$192,2,FALSE()) -> RM001 | D3: CPA_A01 | E3: CPA_A01 | F3: CPA_A01 | G3: CPA_A01.1-1.3 | H3: RME001-020 | I3: : | J3: Cereals | K3: Cereals | L3: Cereals
A4: RME002 | B4: CPA_A01 | C4: =VLOOKUP(A4,new!$A$2:$B$192,2,FALSE()) -> RM002 | D4: CPA_A01 | E4: CPA_A01 | F4: CPA_A01 | G4: CPA_A01.1-1.3 | H4: RME001-020 | I4: : | J4: Green vegetables | K4: Green vegetables | L4: Green leguminous vegetables, vegetables and melons ( excl. edible roots and tubers and sugar beet)
A5: RME003 | B5: CPA_A01 | C5: =VLOOKUP(A5,new!$A$2:$B$192,2,FALSE()) -> RM003 | D5: CPA_A01 | E5: CPA_A01 | F5: CPA_A01 | G5: CPA_A01.1-1.3 | H5: RME001-020 | I5: : | J5: Dried vegetables | K5: Dried vegetables/Pulses | L5: Dried leguminous vegetables
A6: RME004 | B6: CPA_A01 | C6: =VLOOKUP(A6,new!$A$2:$B$192,2,FALSE()) -> RM004 | D6: CPA_A01 | E6: CPA_A01 | F6: CPA_A01 | G6: CPA_A01.1-1.3 | H6: RME001-020 | I6: : | J6: Soya, oil seeds | K6: Soya, oil seeds | L6: Soya beans, groundnuts and cotton seed, other oil seeds
A7: RME005 | B7: CPA_A01 | C7: =VLOOKUP(A7,new!$A$2:$B$192,2,FALSE()) -> RM005 | D7: CPA_A01 | E7: CPA_A01 | F7: CPA_A01 | G7: CPA_A01.1-1.3 | H7: RME001-020 | I7: : | J7: Roots, tubers | K7: Roots, tubers | L7: Edible roots and tubers with high starch or inulin conten
A8: RME006 | B8: CPA_A01 | C8: =VLOOKUP(A8,new!$A$2:$B$192,2,FALSE()) -> RM006 | D8: CPA_A01 | E8: CPA_A01 | F8: CPA_A01 | G8: CPA_A01.1-1.3 | H8: RME001-020 | I8: : | J8: Sugar beet, cane | K8: Sugar beet, cane | L8: Sugar beet and sugar beet seed, sugar cane
A9: RME007 | B9: CPA_A01 | C9: =VLOOKUP(A9,new!$A$2:$B$192,2,FALSE()) -> RM007 | D9: CPA_A01 | E9: CPA_A01 | F9: CPA_A01 | G9: CPA_A01.1-1.3 | H9: RME001-020 | I9: : | J9: Tobacco | K9: Tobacco | L9: Unmanufactured tobacco
A10: RME008 | B10: CPA_A01 | C10: =VLOOKUP(A10,new!$A$2:$B$192,2,FALSE()) -> RM008 | D10: CPA_A01 | E10: CPA_A01 | F10: CPA_A01 | G10: CPA_A01.1-1.3 | H10: RME001-020 | I10: : | J10: Fibre crops | K10: Fibre crops | L10: Fibre crops
A11: RME009 | B11: CPA_A01 | C11: =VLOOKUP(A11,new!$A$2:$B$192,2,FALSE()) -> RM009 | D11: CPA_A01 | E11: CPA_A01 | F11: CPA_A01 | G11: CPA_A01.1-1.3 | H11: RME001-020 | I11: : | J11: Forage crops, grazing | K11: Forage crops, grazing | L11: Forage crops, incl. grazed biomass
A12: RME010 | B12: CPA_A01 | C12: =VLOOKUP(A12,new!$A$2:$B$192,2,FALSE()) -> RM010 | D12: CPA_A01 | E12: CPA_A01 | F12: CPA_A01 | G12: CPA_A01.1-1.3 | H12: RME001-020 | I12: : | J12: Fruits | K12: Fruits | L12: Fruits
A13: RME011 | B13: CPA_A01 | C13: =VLOOKUP(A13,new!$A$2:$B$192,2,FALSE()) -> RM011 | D13: CPA_A01 | E13: CPA_A01 | F13: CPA_A01 | G13: CPA_A01.1-1.3 | H13: RME001-020 | I13: : | J13: Other crops | K13: Other crops | L13: Other crop products
A14: RME012 | B14: CPA_A01 | C14: =VLOOKUP(A14,new!$A$2:$B$192,2,FALSE()) -> RM012 | D14: CPA_A01 | E14: CPA_A01 | F14: CPA_A01 | G14: CPA_A01.4 | H14: RME001-020 | I14: : | J14: Cattle | K14: Cattle | L14: Dairy cattle, liv,e other cattle and buffaloes, live and their semen
... A51: RME049 | B51: CPA_B | C51: =VLOOKUP(A51,new!$A$2:$B$192,2,FALSE()) -> RM042-043 | D51: CPA_B | E51: CPA_B07-09 | F51: CPA_B08_09 | G51: CPA_B07-09 | H51: RME027-056 | I51: RME049-051 | J51: Gravel and sand | K51: Slate | L51: Gravel and sand, excl. mixtures of slag and similar industrial waste products, whether or not incorporating pebbles, gravel, shingle and flint for construction use
A52: RME049a | B52: CPA_B | C52: RM042 | D52: CPA_B | E52: CPA_B07-09 | F52: CPA_B08_09 | G52: CPA_B07-09 | H52: RME027-056 | I52: RME049-051 | J52: Gravel and sand | K52: Gravel and sand | L52: Gravel and sand, excl. mixtures of slag and similar industrial waste products, whether or not incorporating pebbles, gravel, shingle and flint for construction use
A53: RME049b | B53: CPA_B | C53: RM043 | D53: CPA_B | E53: CPA_B07-09 | F53: CPA_B08_09 | G53: CPA_B07-09 | H53: RME027-056 | I53: RME049-051 | J53: Gravel and sand | K53: Gravel and sand | L53: Gravel and sand, excl. mixtures of slag and similar industrial waste products, whether or not incorporating pebbles, gravel, shingle and flint for construction use
A54: RME050 | B54: CPA_B | C54: RM042 | D54: CPA_B | E54: CPA_B07-09 | F54: CPA_B08_09 | G54: CPA_B07-09 | H54: RME027-056 | I54: RME049-051 | J54: Slag, similar waste | K54: Silica | L54: Mixtures of slag and similar industrial waste products, whether or not incorporating pebbles, gravel, shingle and flint for construction use - recycling
A55: RME051 | B55: CPA_B | C55: =VLOOKUP(A55,new!$A$2:$B$192,2,FALSE()) -> RM044 | D55: CPA_B | E55: CPA_B07-09 | F55: CPA_B08_09 | G55: CPA_B07-09 | H55: RME027-056 | I55: RME049-051 | J55: Clays, kaolin | K55: Silica | L55: Clays and kaolin
A56: RME052 | B56: CPA_B | C56: =VLOOKUP(A56,new!$A$2:$B$192,2,FALSE()) -> RM045 | D56: CPA_B | E56: CPA_B07-09 | F56: CPA_B08_09 | G56: CPA_B07-09 | H56: RME027-056 | I56: RME052 | J56: Chemical minerals | K56: Clays, kaolin | L56: Chemical and fertiliser minerals
A57: RME053 | B57: CPA_B | C57: =VLOOKUP(A57,new!$A$2:$B$192,2,FALSE()) -> RM047 | D57: CPA_B | E57: CPA_B07-09 | F57: CPA_B08_09 | G57: CPA_B07-09 | H57: RME027-056 | I57: RME053 | J57: Peat | K57: Chemical and fertiliser minerals | L57: Peat
A58: RME054 | B58: CPA_B | C58: =VLOOKUP(A58,new!$A$2:$B$192,2,FALSE()) -> RM046 | D58: CPA_B | E58: CPA_B07-09 | F58: CPA_B08_09 | G58: CPA_B07-09 | H58: RME027-056 | I58: RME054 | J58: Salt | K58: Mining nec | L58: Salt and pure sodium chloride; sea water
A59: RME055 | B59: CPA_B | C59: =VLOOKUP(A59,new!$A$2:$B$192,2,FALSE()) -> RM047 | D59: CPA_B | E59: CPA_B07-09 | F59: CPA_B08_09 | G59: CPA_B07-09 | H59: RME027-056 | I59: RME055 | J59: Mining nec | K59: Salt | L59: Other mining and quarrying products nec
A60: RME056 | B60: CPA_B | C60: =VLOOKUP(A60,new!$A$2:$B$192,2,FALSE()) -> RM048 | D60: CPA_B | E60: CPA_B07-09 | F60: CPA_B08_09 | G60: CPA_B07-09 | H60: RME027-056 | I60: RME056 | J60: Mining support | K60: Mining nec | L60: Mining support services
A61: RME057 | B61: CPA_C10-12 | C61: =VLOOKUP(A61,new!$A$2:$B$192,2,FALSE()) -> RM049 | D61: CPA_C10-12 | E61: CPA_C10-12 | F61: CPA_C10 | G61: CPA_C10-12 | H61: RME057-067 | I61: RME057 | J61: Preserved meat | K61: Mining support | L61: Preserved meat and meat products
A62: RME058 | B62: CPA_C10-12 | C62: =VLOOKUP(A62,new!$A$2:$B$192,2,FALSE()) -> RM050 | D62: CPA_C10-12 | E62: CPA_C10-12 | F62: CPA_C10 | G62: CPA_C10-12 | H62: RME057-067 | I62: RME058 | J62: Processed fish | K62: Preserved meat | L62: Processed and preserved fish, crustaceans and molluscs
A63: RME059 | B63: CPA_C10-12 | C63: =VLOOKUP(A63,new!$A$2:$B$192,2,FALSE()) -> RM051 | D63: CPA_C10-12 | E63: CPA_C10-12 | F63: CPA_C10 | G63: CPA_C10-12 | H63: RME057-067 | I63: RME059 | J63: Processed fruit, vegetables | K63: Processed fish | L63: Processed and preserved fruit and vegetables
A64: RME060 | B64: CPA_C10-12 | C64: =VLOOKUP(A64,new!$A$2:$B$192,2,FALSE()) -> RM052 | D64: CPA_C10-12 | E64: CPA_C10-12 | F64: CPA_C10 | G64: CPA_C10-12 | H64: RME057-067 | I64: RME060 | J64: Oils | K64: Processed fruit, vegetables | L64: Vegetable and animal oils and fats
A65: RME061 | B65: CPA_C10-12 | C65: =VLOOKUP(A65,new!$A$2:$B$192,2,FALSE()) -> RM053 | D65: CPA_C10-12 | E65: CPA_C10-12 | F65: CPA_C10 | G65: CPA_C10-12 | H65: RME057-067 | I65: RME061 | J65: Dairy | K65: Oils | L65: Dairy products
A66: RME062 | B66: CPA_C10-12 | C66: =VLOOKUP(A66,new!$A$2:$B$192,2,FALSE()) -> RM054 | D66: CPA_C10-12 | E66: CPA_C10-12 | F66: CPA_C10 | G66: CPA_C10-12 | H66: RME057-067 | I66: RME062 | J66: Grain, starches | K66: Dairy | L66: Grain mill products, starches and starch products
... A186: RME182 | B186: CPA_T | C186: =VLOOKUP(A186,new!$A$2:$B$192,2,FALSE()) -> RM165 | D186: RME182 | E186: CPA_T | F186: CPA_T | G186: CPA_T | H186: RME140-182nec | I186: RME182 | J186: Household services | K186: Services nec | L186: Services of households as employers; undifferentiated goods and services produced by households for own use
A187: RME181a | B187: CPA_T | C187: RM164 | D187: RME182 | E187: CPA_T | F187: CPA_T | G187: CPA_T | H187: RME140-182nec | I187: RME182 | J187: Services nec | K187: Household services | L187: Services of households as employers; undifferentiated goods and services produced by households for own use
A188: RME181b | B188: CPA_T | C188: RM166 | D188: RME182 | E188: CPA_T | F188: CPA_T | G188: CPA_T | H188: RME140-182nec | I188: RME182 | J188: Services nec | K188: Services nec | L188: Services of households as employers; undifferentiated goods and services produced by households for own use
A189: GVA | B189: GVA | C189: GVA | D189: GVA | E189: GVA | F189: GVA | G189: GVA | H189: GVA | J189: Gross value added | K189: Extraterritorial organisations
A190: HFCE | B190: HFCE | C190: =VLOOKUP(A190,new!$A$2:$B$192,2,FALSE()) -> HFCE | D190: HFCE | E190: HFCE | F190: HFCE | G190: HFCE | H190: HFCE | J190: Household consumption | K190: Gross value added
A191: NFCE | B191: NFCE | C191: =VLOOKUP(A191,new!$A$2:$B$192,2,FALSE()) -> NFCE | D191: NFCE | E191: NFCE | F191: NFCE | G191: NFCE | H191: NFCE | J191: Government consumption
A192: GFCE | B192: GFCE | C192: =VLOOKUP(A192,new!$A$2:$B$192,2,FALSE()) -> GFCE | D192: GFCE | E192: GFCE | F192: GFCE | G192: GFCE | H192: GFCE | J192: NPISH consumption
A193: INV | B193: INV | C193: =VLOOKUP(A193,new!$A$2:$B$192,2,FALSE()) -> INV | D193: INV | E193: INV | F193: INV | G193: INV | H193: INV | J193: Investment
A194: CINV | B194: CINV | C194: =VLOOKUP(A194,new!$A$2:$B$192,2,FALSE()) -> CINV | D194: CINV | E194: CINV | F194: CINV | G194: CINV | H194: CINV | J194: Inventory changes
A195: OUT | B195: OUT | C195: =VLOOKUP(A195,new!$A$2:$B$192,2,FALSE()) -> OUT | D195: OUT | E195: OUT | F195: OUT | G195: OUT | H195: OUT | J195: Output
A196: EXP | B196: EXP | C196: =VLOOKUP(A196,new!$A$2:$B$192,2,FALSE()) -> EXP | D196: EXP | E196: EXP | F196: EXP | G196: EXP | H196: EXP | J196: Exports
A197: EXP_i | B197: EXP_i | D197: EXP_i | E197: EXP_i | F197: EXP_i | G197: EXP_i | H197: EXP_i | J197: Exports intra-EU
A198: EXP_e | B198: EXP_e | D198: EXP_e | E198: EXP_e | F198: EXP_e | G198: EXP_e | H198: EXP_e | J198: Exports extra-EU
A199: IMP_i | B199: IMP_i | D199: IMP_i | E199: IMP_i | F199: IMP_i | G199: IMP_i | H199: IMP_i | J199: Intra-EU imports
A200: IMP_e | B200: IMP_e | D200: IMP_e | E200: IMP_e | F200: IMP_e | G200: IMP_e | H200: IMP_e | J200: Extra-EU imports
A201: RME001-019 | B201: CPA_A01
A202: RME022-056 | B202: CPA_B
A203: RME057-067 | B203: CPA_C10-12
A204: RME068-070 | B204: CPA_C13-15
A205: RME072-073 | B205: CPA_C17
A206: RME075-076 | B206: CPA_C19
A207: RME077-084 | B207: CPA_C20
A208: RME086-087 | B208: CPA_C22
A209: RME088-095 | B209: CPA_C23
A210: RME096-117 | B210: CPA_C24
A211: RME118-124 | B211: CPA_C25
A212: RME129-132 | B212: CPA_C30
... A214: RME141-143 | B214: CPA_D35
A215: : | B215: : | F215: : | J215: Not assignable
A216: TOTAL | B216: TOTAL | D216: TOTAL | F216: TOTAL | G216: TOTAL | H216: TOTAL
